[{"date": "2025-04-30", "open": 2005.0, "high": 2040.0, "low": 2005.0, "close": 2040.0, "volume": 30479, "ma5": null, "ma20": null, "ma60": null, "ma120": null, "rsi": null, "macd": null, "macd_signal": null, "macd_hist": null, "bb_upper": null, "bb_mid": null, "bb_lower": null}, {"date": "2025-05-02", "open": 2020.0, "high": 2050.0, "low": 2020.0, "close": 2050.0, "volume": 12546, "ma5": null, "ma20": null, "ma60": null, "ma120": null, "rsi": null, "macd": null, "macd_signal": null, "macd_hist": null, "bb_upper": null, "bb_mid": null, "bb_lower": null}, {"date": "2025-05-07", "open": 2025.0, "high": 2050.0, "low": 2025.0, "close": 2040.0, "volume": 5232, "ma5": null, "ma20": null, "ma60": null, "ma120": null, "rsi": null, "macd": null, "macd_signal": null, "macd_hist": null, "bb_upper": null, "bb_mid": null, "bb_lower": null}, {"date": "2025-05-08", "open": 2030.0, "high": 2050.0, "low": 2030.0, "close": 2040.0, "volume": 13823, "ma5": null, "ma20": null, "ma60": null, "ma120": null, "rsi": null, "macd": null, "macd_signal": null, "macd_hist": null, "bb_upper": null, "bb_mid": null, "bb_lower": null}, {"date": "2025-05-09", "open": 2030.0, "high": 2050.0, "low": 2030.0, "close": 2040.0, "volume": 51407, "ma5": 2042.0, "ma20": null, "ma60": null, "ma120": null, "rsi": null, "macd": null, "macd_signal": null, "macd_hist": null, "bb_upper": null, "bb_mid": null, "bb_lower": null}, {"date": "2025-05-12", "open": 2030.0, "high": 2050.0, "low": 2030.0, "close": 2040.0, "volume": 19905, "ma5": 2042.0, "ma20": null, "ma60": null, "ma120": null, "rsi": null, "macd": null, "macd_signal": null, "macd_hist": null, "bb_upper": null, "bb_mid": null, "bb_lower": null}, {"date": "2025-05-13", "open": 2030.0, "high": 2055.0, "low": 2030.0, "close": 2055.0, "volume": 16072, "ma5": 2043.0, "ma20": null, "ma60": null, "ma120": null, "rsi": null, "macd": null, "macd_signal": null, "macd_hist": null, "bb_upper": null, "bb_mid": null, "bb_lower": null}, {"date": "2025-05-14", "open": 2040.0, "high": 2055.0, "low": 2035.0, "close": 2055.0, "volume": 46920, "ma5": 2046.0, "ma20": null, "ma60": null, "ma120": null, "rsi": null, "macd": null, "macd_signal": null, "macd_hist": null, "bb_upper": null, "bb_mid": null, "bb_lower": null}, {"date": "2025-05-15", "open": 2050.0, "high": 2060.0, "low": 2045.0, "close": 2060.0, "volume": 2199, "ma5": 2050.0, "ma20": null, "ma60": null, "ma120": null, "rsi": null, "macd": null, "macd_signal": null, "macd_hist": null, "bb_upper": null, "bb_mid": null, "bb_lower": null}, {"date": "2025-05-16", "open": 2050.0, "high": 2055.0, "low": 2045.0, "close": 2055.0, "volume": 1123, "ma5": 2053.0, "ma20": null, "ma60": null, "ma120": null, "rsi": null, "macd": null, "macd_signal": null, "macd_hist": null, "bb_upper": null, "bb_mid": null, "bb_lower": null}, {"date": "2025-05-19", "open": 2055.0, "high": 2065.0, "low": 2045.0, "close": 2060.0, "volume": 7053, "ma5": 2057.0, "ma20": null, "ma60": null, "ma120": null, "rsi": null, "macd": null, "macd_signal": null, "macd_hist": null, "bb_upper": null, "bb_mid": null, "bb_lower": null}, {"date": "2025-05-20", "open": 2050.0, "high": 2067.0, "low": 2045.0, "close": 2060.0, "volume": 9438, "ma5": 2058.0, "ma20": null, "ma60": null, "ma120": null, "rsi": null, "macd": null, "macd_signal": null, "macd_hist": null, "bb_upper": null, "bb_mid": null, "bb_lower": null}, {"date": "2025-05-21", "open": 2055.0, "high": 2065.0, "low": 2050.0, "close": 2050.0, "volume": 6057, "ma5": 2057.0, "ma20": null, "ma60": null, "ma120": null, "rsi": null, "macd": null, "macd_signal": null, "macd_hist": null, "bb_upper": null, "bb_mid": null, "bb_lower": null}, {"date": "2025-05-22", "open": 2050.0, "high": 2055.0, "low": 2040.0, "close": 2050.0, "volume": 8708, "ma5": 2055.0, "ma20": null, "ma60": null, "ma120": null, "rsi": 54.04, "macd": null, "macd_signal": null, "macd_hist": null, "bb_upper": null, "bb_mid": null, "bb_lower": null}, {"date": "2025-05-23", "open": 2050.0, "high": 2055.0, "low": 2045.0, "close": 2050.0, "volume": 14291, "ma5": 2054.0, "ma20": null, "ma60": null, "ma120": null, "rsi": 54.04, "macd": null, "macd_signal": null, "macd_hist": null, "bb_upper": null, "bb_mid": null, "bb_lower": null}, {"date": "2025-05-26", "open": 2050.0, "high": 2065.0, "low": 2045.0, "close": 2060.0, "volume": 6744, "ma5": 2054.0, "ma20": null, "ma60": null, "ma120": null, "rsi": 64.8, "macd": null, "macd_signal": null, "macd_hist": null, "bb_upper": null, "bb_mid": null, "bb_lower": null}, {"date": "2025-05-27", "open": 2050.0, "high": 2060.0, "low": 2045.0, "close": 2050.0, "volume": 1423, "ma5": 2052.0, "ma20": null, "ma60": null, "ma120": null, "rsi": 51.75, "macd": null, "macd_signal": null, "macd_hist": null, "bb_upper": null, "bb_mid": null, "bb_lower": null}, {"date": "2025-05-28", "open": 2060.0, "high": 2070.0, "low": 2045.0, "close": 2065.0, "volume": 7982, "ma5": 2055.0, "ma20": null, "ma60": null, "ma120": null, "rsi": 63.6, "macd": null, "macd_signal": null, "macd_hist": null, "bb_upper": null, "bb_mid": null, "bb_lower": null}, {"date": "2025-05-29", "open": 2050.0, "high": 2070.0, "low": 2045.0, "close": 2060.0, "volume": 11295, "ma5": 2057.0, "ma20": null, "ma60": null, "ma120": null, "rsi": 58.45, "macd": null, "macd_signal": null, "macd_hist": null, "bb_upper": null, "bb_mid": null, "bb_lower": null}, {"date": "2025-05-30", "open": 2050.0, "high": 2065.0, "low": 2050.0, "close": 2055.0, "volume": 2930, "ma5": 2058.0, "ma20": 2051.75, "ma60": null, "ma120": null, "rsi": 53.76, "macd": null, "macd_signal": null, "macd_hist": null, "bb_upper": 2067.65, "bb_mid": 2051.75, "bb_lower": 2035.85}, {"date": "2025-06-02", "open": 2050.0, "high": 2060.0, "low": 2040.0, "close": 2055.0, "volume": 4422, "ma5": 2057.0, "ma20": 2052.5, "ma60": null, "ma120": null, "rsi": 53.76, "macd": null, "macd_signal": null, "macd_hist": null, "bb_upper": 2067.5, "bb_mid": 2052.5, "bb_lower": 2037.5}, {"date": "2025-06-04", "open": 2050.0, "high": 2060.0, "low": 2050.0, "close": 2055.0, "volume": 371, "ma5": 2058.0, "ma20": 2052.75, "ma60": null, "ma120": null, "rsi": 53.76, "macd": null, "macd_signal": null, "macd_hist": null, "bb_upper": 2067.74, "bb_mid": 2052.75, "bb_lower": 2037.76}, {"date": "2025-06-05", "open": 2050.0, "high": 2060.0, "low": 2050.0, "close": 2055.0, "volume": 1467, "ma5": 2056.0, "ma20": 2053.5, "ma60": null, "ma120": null, "rsi": 53.76, "macd": null, "macd_signal": null, "macd_hist": null, "bb_upper": 2067.32, "bb_mid": 2053.5, "bb_lower": 2039.68}, {"date": "2025-06-09", "open": 2055.0, "high": 2070.0, "low": 2050.0, "close": 2070.0, "volume": 7060, "ma5": 2058.0, "ma20": 2055.0, "ma60": null, "ma120": null, "rsi": 65.07, "macd": null, "macd_signal": null, "macd_hist": null, "bb_upper": 2069.14, "bb_mid": 2055.0, "bb_lower": 2040.86}, {"date": "2025-06-10", "open": 2060.0, "high": 2070.0, "low": 2055.0, "close": 2070.0, "volume": 3107, "ma5": 2061.0, "ma20": 2056.5, "ma60": null, "ma120": null, "rsi": 65.07, "macd": null, "macd_signal": null, "macd_hist": null, "bb_upper": 2070.32, "bb_mid": 2056.5, "bb_lower": 2042.68}, {"date": "2025-06-11", "open": 2075.0, "high": 2075.0, "low": 2060.0, "close": 2075.0, "volume": 3752, "ma5": 2065.0, "ma20": 2058.25, "ma60": null, "ma120": null, "rsi": 68.08, "macd": 5.8, "macd_signal": null, "macd_hist": null, "bb_upper": 2072.13, "bb_mid": 2058.25, "bb_lower": 2044.37}, {"date": "2025-06-12", "open": 2060.0, "high": 2075.0, "low": 2055.0, "close": 2065.0, "volume": 6343, "ma5": 2067.0, "ma20": 2058.75, "ma60": null, "ma120": null, "rsi": 57.4, "macd": 5.64, "macd_signal": null, "macd_hist": null, "bb_upper": 2072.85, "bb_mid": 2058.75, "bb_lower": 2044.65}, {"date": "2025-06-13", "open": 2055.0, "high": 2070.0, "low": 2050.0, "close": 2055.0, "volume": 1707, "ma5": 2067.0, "ma20": 2058.75, "ma60": null, "ma120": null, "rsi": 49.11, "macd": 4.65, "macd_signal": null, "macd_hist": null, "bb_upper": 2072.85, "bb_mid": 2058.75, "bb_lower": 2044.65}, {"date": "2025-06-16", "open": 2055.0, "high": 2065.0, "low": 2040.0, "close": 2065.0, "volume": 6819, "ma5": 2066.0, "ma20": 2059.0, "ma60": null, "ma120": null, "rsi": 55.96, "macd": 4.61, "macd_signal": null, "macd_hist": null, "bb_upper": 2073.35, "bb_mid": 2059.0, "bb_lower": 2044.65}, {"date": "2025-06-17", "open": 2045.0, "high": 2065.0, "low": 2045.0, "close": 2065.0, "volume": 3193, "ma5": 2065.0, "ma20": 2059.5, "ma60": null, "ma120": null, "rsi": 55.96, "macd": 4.54, "macd_signal": null, "macd_hist": null, "bb_upper": 2073.96, "bb_mid": 2059.5, "bb_lower": 2045.04}, {"date": "2025-06-18", "open": 2050.0, "high": 2065.0, "low": 2050.0, "close": 2065.0, "volume": 2239, "ma5": 2063.0, "ma20": 2059.75, "ma60": null, "ma120": null, "rsi": 55.96, "macd": 4.43, "macd_signal": null, "macd_hist": null, "bb_upper": 2074.4, "bb_mid": 2059.75, "bb_lower": 2045.1}, {"date": "2025-06-19", "open": 2050.0, "high": 2057.0, "low": 2050.0, "close": 2055.0, "volume": 4062, "ma5": 2061.0, "ma20": 2059.5, "ma60": null, "ma120": null, "rsi": 47.9, "macd": 3.49, "macd_signal": null, "macd_hist": null, "bb_upper": 2074.3, "bb_mid": 2059.5, "bb_lower": 2044.7}, {"date": "2025-06-20", "open": 2050.0, "high": 2055.0, "low": 2040.0, "close": 2050.0, "volume": 11474, "ma5": 2060.0, "ma20": 2059.5, "ma60": null, "ma120": null, "rsi": 44.46, "macd": 2.32, "macd_signal": null, "macd_hist": null, "bb_upper": 2074.3, "bb_mid": 2059.5, "bb_lower": 2044.7}, {"date": "2025-06-23", "open": 2050.0, "high": 2060.0, "low": 2042.0, "close": 2055.0, "volume": 7628, "ma5": 2058.0, "ma20": 2059.75, "ma60": null, "ma120": null, "rsi": 48.45, "macd": 1.77, "macd_signal": 3.75, "macd_hist": -1.98, "bb_upper": 2074.06, "bb_mid": 2059.75, "bb_lower": 2045.44}, {"date": "2025-06-24", "open": 2045.0, "high": 2050.0, "low": 2035.0, "close": 2045.0, "volume": 5875, "ma5": 2054.0, "ma20": 2059.5, "ma60": null, "ma120": null, "rsi": 41.95, "macd": 0.53, "macd_signal": 3.11, "macd_hist": -2.58, "bb_upper": 2074.63, "bb_mid": 2059.5, "bb_lower": 2044.37}, {"date": "2025-06-25", "open": 2040.0, "high": 2045.0, "low": 2040.0, "close": 2045.0, "volume": 906, "ma5": 2050.0, "ma20": 2058.75, "ma60": null, "ma120": null, "rsi": 41.95, "macd": -0.45, "macd_signal": 2.4, "macd_hist": -2.85, "bb_upper": 2075.14, "bb_mid": 2058.75, "bb_lower": 2042.36}, {"date": "2025-06-26", "open": 2040.0, "high": 2045.0, "low": 2035.0, "close": 2045.0, "volume": 1960, "ma5": 2048.0, "ma20": 2058.5, "ma60": null, "ma120": null, "rsi": 41.95, "macd": -1.22, "macd_signal": 1.67, "macd_hist": -2.89, "bb_upper": 2075.56, "bb_mid": 2058.5, "bb_lower": 2041.44}, {"date": "2025-06-27", "open": 2040.0, "high": 2055.0, "low": 2040.0, "close": 2055.0, "volume": 10127, "ma5": 2049.0, "ma20": 2058.0, "ma60": null, "ma120": null, "rsi": 50.28, "macd": -1.01, "macd_signal": 1.14, "macd_hist": -2.14, "bb_upper": 2074.85, "bb_mid": 2058.0, "bb_lower": 2041.15}, {"date": "2025-06-30", "open": 2050.0, "high": 2060.0, "low": 2040.0, "close": 2060.0, "volume": 11963, "ma5": 2050.0, "ma20": 2058.0, "ma60": null, "ma120": null, "rsi": 53.85, "macd": -0.43, "macd_signal": 0.82, "macd_hist": -1.25, "bb_upper": 2074.85, "bb_mid": 2058.0, "bb_lower": 2041.15}, {"date": "2025-07-01", "open": 2060.0, "high": 2065.0, "low": 2060.0, "close": 2060.0, "volume": 9296, "ma5": 2053.0, "ma20": 2058.25, "ma60": null, "ma120": null, "rsi": 53.85, "macd": 0.03, "macd_signal": 0.66, "macd_hist": -0.64, "bb_upper": 2075.07, "bb_mid": 2058.25, "bb_lower": 2041.43}, {"date": "2025-07-02", "open": 2055.0, "high": 2055.0, "low": 2055.0, "close": 2055.0, "volume": 1036, "ma5": 2055.0, "ma20": 2058.25, "ma60": null, "ma120": null, "rsi": 49.71, "macd": -0.01, "macd_signal": 0.53, "macd_hist": -0.54, "bb_upper": 2075.07, "bb_mid": 2058.25, "bb_lower": 2041.43}, {"date": "2025-07-03", "open": 2050.0, "high": 2055.0, "low": 2050.0, "close": 2055.0, "volume": 821, "ma5": 2057.0, "ma20": 2058.25, "ma60": null, "ma120": null, "rsi": 49.71, "macd": -0.04, "macd_signal": 0.41, "macd_hist": -0.46, "bb_upper": 2075.07, "bb_mid": 2058.25, "bb_lower": 2041.43}, {"date": "2025-07-04", "open": 2040.0, "high": 2050.0, "low": 2020.0, "close": 2050.0, "volume": 44356, "ma5": 2056.0, "ma20": 2058.0, "ma60": null, "ma120": null, "rsi": 45.65, "macd": -0.47, "macd_signal": 0.24, "macd_hist": -0.71, "bb_upper": 2075.15, "bb_mid": 2058.0, "bb_lower": 2040.85}, {"date": "2025-07-07", "open": 2050.0, "high": 2050.0, "low": 2045.0, "close": 2045.0, "volume": 499, "ma5": 2053.0, "ma20": 2056.75, "ma60": null, "ma120": null, "rsi": 41.95, "macd": -1.19, "macd_signal": -0.05, "macd_hist": -1.14, "bb_upper": 2073.86, "bb_mid": 2056.75, "bb_lower": 2039.64}, {"date": "2025-07-08", "open": 2045.0, "high": 2045.0, "low": 2020.0, "close": 2040.0, "volume": 35613, "ma5": 2049.0, "ma20": 2055.25, "ma60": null, "ma120": null, "rsi": 38.59, "macd": -2.15, "macd_signal": -0.47, "macd_hist": -1.68, "bb_upper": 2072.71, "bb_mid": 2055.25, "bb_lower": 2037.79}, {"date": "2025-07-09", "open": 2040.0, "high": 2040.0, "low": 2025.0, "close": 2035.0, "volume": 1962, "ma5": 2045.0, "ma20": 2053.25, "ma60": null, "ma120": null, "rsi": 35.52, "macd": -3.27, "macd_signal": -1.03, "macd_hist": -2.24, "bb_upper": 2070.36, "bb_mid": 2053.25, "bb_lower": 2036.14}, {"date": "2025-07-10", "open": 2030.0, "high": 2045.0, "low": 2030.0, "close": 2030.0, "volume": 595, "ma5": 2040.0, "ma20": 2051.5, "ma60": null, "ma120": null, "rsi": 32.72, "macd": -4.51, "macd_signal": -1.72, "macd_hist": -2.78, "bb_upper": 2070.5, "bb_mid": 2051.5, "bb_lower": 2032.5}, {"date": "2025-07-11", "open": 2030.0, "high": 2030.0, "low": 2020.0, "close": 2025.0, "volume": 4632, "ma5": 2035.0, "ma20": 2050.0, "ma60": null, "ma120": null, "rsi": 30.16, "macd": -5.83, "macd_signal": -2.54, "macd_hist": -3.28, "bb_upper": 2072.14, "bb_mid": 2050.0, "bb_lower": 2027.86}, {"date": "2025-07-14", "open": 2025.0, "high": 2030.0, "low": 2020.0, "close": 2030.0, "volume": 5958, "ma5": 2032.0, "ma20": 2048.25, "ma60": null, "ma120": null, "rsi": 35.59, "macd": -6.4, "macd_signal": -3.31, "macd_hist": -3.08, "bb_upper": 2070.89, "bb_mid": 2048.25, "bb_lower": 2025.61}, {"date": "2025-07-15", "open": 2025.0, "high": 2030.0, "low": 2020.0, "close": 2025.0, "volume": 20109, "ma5": 2029.0, "ma20": 2046.25, "ma60": null, "ma120": null, "rsi": 32.84, "macd": -7.17, "macd_signal": -4.09, "macd_hist": -3.08, "bb_upper": 2069.68, "bb_mid": 2046.25, "bb_lower": 2022.82}, {"date": "2025-07-16", "open": 2025.0, "high": 2030.0, "low": 2025.0, "close": 2030.0, "volume": 5947, "ma5": 2028.0, "ma20": 2044.5, "ma60": null, "ma120": null, "rsi": 38.0, "macd": -7.29, "macd_signal": -4.73, "macd_hist": -2.56, "bb_upper": 2067.28, "bb_mid": 2044.5, "bb_lower": 2021.72}, {"date": "2025-07-17", "open": 2030.0, "high": 2040.0, "low": 2025.0, "close": 2035.0, "volume": 8511, "ma5": 2029.0, "ma20": 2043.5, "ma60": null, "ma120": null, "rsi": 42.73, "macd": -6.91, "macd_signal": -5.16, "macd_hist": -1.74, "bb_upper": 2066.11, "bb_mid": 2043.5, "bb_lower": 2020.89}, {"date": "2025-07-18", "open": 2030.0, "high": 2040.0, "low": 2030.0, "close": 2035.0, "volume": 1286, "ma5": 2031.0, "ma20": 2042.75, "ma60": null, "ma120": null, "rsi": 42.73, "macd": -6.53, "macd_signal": -5.43, "macd_hist": -1.09, "bb_upper": 2065.44, "bb_mid": 2042.75, "bb_lower": 2020.06}, {"date": "2025-07-21", "open": 2025.0, "high": 2035.0, "low": 2025.0, "close": 2035.0, "volume": 17057, "ma5": 2032.0, "ma20": 2041.75, "ma60": null, "ma120": null, "rsi": 42.73, "macd": -6.15, "macd_signal": -5.58, "macd_hist": -0.57, "bb_upper": 2063.95, "bb_mid": 2041.75, "bb_lower": 2019.55}, {"date": "2025-07-22", "open": 2030.0, "high": 2040.0, "low": 2030.0, "close": 2040.0, "volume": 2763, "ma5": 2035.0, "ma20": 2041.5, "ma60": null, "ma120": null, "rsi": 47.72, "macd": -5.39, "macd_signal": -5.54, "macd_hist": 0.15, "bb_upper": 2063.66, "bb_mid": 2041.5, "bb_lower": 2019.34}, {"date": "2025-07-23", "open": 2045.0, "high": 2045.0, "low": 2035.0, "close": 2040.0, "volume": 17157, "ma5": 2037.0, "ma20": 2041.25, "ma60": null, "ma120": null, "rsi": 47.72, "macd": -4.73, "macd_signal": -5.38, "macd_hist": 0.65, "bb_upper": 2063.36, "bb_mid": 2041.25, "bb_lower": 2019.14}, {"date": "2025-07-24", "open": 2050.0, "high": 2050.0, "low": 2035.0, "close": 2040.0, "volume": 6129, "ma5": 2038.0, "ma20": 2041.0, "ma60": null, "ma120": null, "rsi": 47.72, "macd": -4.17, "macd_signal": -5.14, "macd_hist": 0.97, "bb_upper": 2063.05, "bb_mid": 2041.0, "bb_lower": 2018.95}, {"date": "2025-07-25", "open": 2040.0, "high": 2040.0, "low": 2020.0, "close": 2025.0, "volume": 28783, "ma5": 2036.0, "ma20": 2039.5, "ma60": null, "ma120": null, "rsi": 35.98, "macd": -4.87, "macd_signal": -5.08, "macd_hist": 0.21, "bb_upper": 2061.61, "bb_mid": 2039.5, "bb_lower": 2017.39}, {"date": "2025-07-28", "open": 2030.0, "high": 2035.0, "low": 2020.0, "close": 2035.0, "volume": 18819, "ma5": 2036.0, "ma20": 2038.25, "ma60": null, "ma120": null, "rsi": 45.59, "macd": -4.57, "macd_signal": -4.98, "macd_hist": 0.41, "bb_upper": 2058.32, "bb_mid": 2038.25, "bb_lower": 2018.18}, {"date": "2025-07-29", "open": 2035.0, "high": 2035.0, "low": 2020.0, "close": 2035.0, "volume": 17920, "ma5": 2035.0, "ma20": 2037.0, "ma60": 2049.0, "ma120": null, "rsi": 45.59, "macd": -4.28, "macd_signal": -4.84, "macd_hist": 0.56, "bb_upper": 2054.44, "bb_mid": 2037.0, "bb_lower": 2019.56}, {"date": "2025-07-30", "open": 2035.0, "high": 2035.0, "low": 2020.0, "close": 2025.0, "volume": 30275, "ma5": 2032.0, "ma20": 2035.5, "ma60": 2048.75, "ma120": null, "rsi": 38.83, "macd": -4.8, "macd_signal": -4.83, "macd_hist": 0.03, "bb_upper": 2051.59, "bb_mid": 2035.5, "bb_lower": 2019.41}, {"date": "2025-07-31", "open": 2030.0, "high": 2030.0, "low": 2020.0, "close": 2025.0, "volume": 11471, "ma5": 2029.0, "ma20": 2034.0, "ma60": 2048.33, "ma120": null, "rsi": 38.83, "macd": -5.16, "macd_signal": -4.9, "macd_hist": -0.26, "bb_upper": 2048.0, "bb_mid": 2034.0, "bb_lower": 2020.0}, {"date": "2025-08-01", "open": 2020.0, "high": 2025.0, "low": 2015.0, "close": 2025.0, "volume": 10039, "ma5": 2029.0, "ma20": 2032.75, "ma60": 2048.08, "ma120": null, "rsi": 38.83, "macd": -5.37, "macd_signal": -4.99, "macd_hist": -0.38, "bb_upper": 2045.19, "bb_mid": 2032.75, "bb_lower": 2020.31}, {"date": "2025-08-04", "open": 2010.0, "high": 2025.0, "low": 2010.0, "close": 2025.0, "volume": 3185, "ma5": 2027.0, "ma20": 2031.75, "ma60": 2047.83, "ma120": null, "rsi": 38.83, "macd": -5.49, "macd_signal": -5.09, "macd_hist": -0.39, "bb_upper": 2043.27, "bb_mid": 2031.75, "bb_lower": 2020.23}, {"date": "2025-08-05", "open": 2025.0, "high": 2025.0, "low": 2015.0, "close": 2020.0, "volume": 874, "ma5": 2024.0, "ma20": 2030.75, "ma60": 2047.5, "ma120": null, "rsi": 35.31, "macd": -5.91, "macd_signal": -5.25, "macd_hist": -0.65, "bb_upper": 2042.7, "bb_mid": 2030.75, "bb_lower": 2018.8}, {"date": "2025-08-06", "open": 2015.0, "high": 2020.0, "low": 2015.0, "close": 2020.0, "volume": 807, "ma5": 2023.0, "ma20": 2030.0, "ma60": 2047.17, "ma120": null, "rsi": 35.31, "macd": -6.17, "macd_signal": -5.44, "macd_hist": -0.73, "bb_upper": 2042.65, "bb_mid": 2030.0, "bb_lower": 2017.35}, {"date": "2025-08-07", "open": 2020.0, "high": 2020.0, "low": 2015.0, "close": 2020.0, "volume": 12205, "ma5": 2022.0, "ma20": 2029.5, "ma60": 2046.58, "ma120": null, "rsi": 35.31, "macd": -6.31, "macd_signal": -5.61, "macd_hist": -0.7, "bb_upper": 2042.88, "bb_mid": 2029.5, "bb_lower": 2016.12}, {"date": "2025-08-08", "open": 2010.0, "high": 2025.0, "low": 2010.0, "close": 2010.0, "volume": 22431, "ma5": 2019.0, "ma20": 2028.75, "ma60": 2045.83, "ma120": null, "rsi": 28.79, "macd": -7.14, "macd_signal": -5.92, "macd_hist": -1.22, "bb_upper": 2044.52, "bb_mid": 2028.75, "bb_lower": 2012.98}, {"date": "2025-08-11", "open": 2010.0, "high": 2020.0, "low": 2005.0, "close": 2020.0, "volume": 6581, "ma5": 2018.0, "ma20": 2028.25, "ma60": 2045.17, "ma120": null, "rsi": 40.6, "macd": -6.91, "macd_signal": -6.12, "macd_hist": -0.8, "bb_upper": 2044.46, "bb_mid": 2028.25, "bb_lower": 2012.04}, {"date": "2025-08-12", "open": 2020.0, "high": 2025.0, "low": 2010.0, "close": 2020.0, "volume": 4534, "ma5": 2018.0, "ma20": 2028.0, "ma60": 2044.58, "ma120": null, "rsi": 40.6, "macd": -6.66, "macd_signal": -6.23, "macd_hist": -0.43, "bb_upper": 2044.55, "bb_mid": 2028.0, "bb_lower": 2011.45}, {"date": "2025-08-13", "open": 2020.0, "high": 2030.0, "low": 2015.0, "close": 2020.0, "volume": 16056, "ma5": 2018.0, "ma20": 2027.5, "ma60": 2043.92, "ma120": null, "rsi": 40.6, "macd": -6.38, "macd_signal": -6.26, "macd_hist": -0.12, "bb_upper": 2044.38, "bb_mid": 2027.5, "bb_lower": 2010.62}, {"date": "2025-08-14", "open": 2020.0, "high": 2025.0, "low": 2015.0, "close": 2025.0, "volume": 17752, "ma5": 2019.0, "ma20": 2027.0, "ma60": 2043.33, "ma120": null, "rsi": 46.18, "macd": -5.69, "macd_signal": -6.14, "macd_hist": 0.45, "bb_upper": 2043.55, "bb_mid": 2027.0, "bb_lower": 2010.45}, {"date": "2025-08-18", "open": 2025.0, "high": 2025.0, "low": 2015.0, "close": 2025.0, "volume": 8851, "ma5": 2022.0, "ma20": 2026.5, "ma60": 2042.92, "ma120": null, "rsi": 46.18, "macd": -5.09, "macd_signal": -5.93, "macd_hist": 0.84, "bb_upper": 2042.66, "bb_mid": 2026.5, "bb_lower": 2010.34}, {"date": "2025-08-19", "open": 2015.0, "high": 2025.0, "low": 2015.0, "close": 2020.0, "volume": 1274, "ma5": 2022.0, "ma20": 2025.75, "ma60": 2042.42, "ma120": null, "rsi": 41.64, "macd": -4.96, "macd_signal": -5.74, "macd_hist": 0.78, "bb_upper": 2041.65, "bb_mid": 2025.75, "bb_lower": 2009.85}, {"date": "2025-08-20", "open": 2015.0, "high": 2020.0, "low": 2015.0, "close": 2020.0, "volume": 624, "ma5": 2022.0, "ma20": 2024.75, "ma60": 2041.92, "ma120": null, "rsi": 41.64, "macd": -4.8, "macd_signal": -5.55, "macd_hist": 0.75, "bb_upper": 2039.4, "bb_mid": 2024.75, "bb_lower": 2010.1}, {"date": "2025-08-21", "open": 2020.0, "high": 2025.0, "low": 2015.0, "close": 2025.0, "volume": 5051, "ma5": 2023.0, "ma20": 2024.0, "ma60": 2041.33, "ma120": null, "rsi": 47.61, "macd": -4.22, "macd_signal": -5.28, "macd_hist": 1.07, "bb_upper": 2036.88, "bb_mid": 2024.0, "bb_lower": 2011.12}, {"date": "2025-08-22", "open": 2015.0, "high": 2025.0, "low": 2015.0, "close": 2020.0, "volume": 4913, "ma5": 2022.0, "ma20": 2023.0, "ma60": 2040.83, "ma120": null, "rsi": 42.89, "macd": -4.11, "macd_signal": -5.05, "macd_hist": 0.94, "bb_upper": 2033.68, "bb_mid": 2023.0, "bb_lower": 2012.32}, {"date": "2025-08-25", "open": 2020.0, "high": 2025.0, "low": 2020.0, "close": 2020.0, "volume": 4072, "ma5": 2021.0, "ma20": 2022.75, "ma60": 2040.08, "ma120": null, "rsi": 42.89, "macd": -3.99, "macd_signal": -4.84, "macd_hist": 0.85, "bb_upper": 2033.46, "bb_mid": 2022.75, "bb_lower": 2012.04}, {"date": "2025-08-26", "open": 2020.0, "high": 2020.0, "low": 2010.0, "close": 2015.0, "volume": 26385, "ma5": 2020.0, "ma20": 2021.75, "ma60": 2039.33, "ma120": null, "rsi": 38.46, "macd": -4.24, "macd_signal": -4.72, "macd_hist": 0.48, "bb_upper": 2031.38, "bb_mid": 2021.75, "bb_lower": 2012.12}, {"date": "2025-08-27", "open": 2020.0, "high": 2020.0, "low": 2010.0, "close": 2012.0, "volume": 17022, "ma5": 2018.4, "ma20": 2020.6, "ma60": 2038.62, "ma120": null, "rsi": 36.06, "macd": -4.63, "macd_signal": -4.7, "macd_hist": 0.07, "bb_upper": 2029.05, "bb_mid": 2020.6, "bb_lower": 2012.15}, {"date": "2025-08-28", "open": 2010.0, "high": 2015.0, "low": 2010.0, "close": 2010.0, "volume": 918, "ma5": 2015.4, "ma20": 2019.85, "ma60": 2037.87, "ma120": null, "rsi": 34.51, "macd": -5.04, "macd_signal": -4.77, "macd_hist": -0.27, "bb_upper": 2029.22, "bb_mid": 2019.85, "bb_lower": 2010.48}, {"date": "2025-08-29", "open": 2010.0, "high": 2015.0, "low": 2010.0, "close": 2015.0, "volume": 12002, "ma5": 2014.4, "ma20": 2019.35, "ma60": 2037.2, "ma120": null, "rsi": 41.3, "macd": -4.91, "macd_signal": -4.8, "macd_hist": -0.11, "bb_upper": 2028.63, "bb_mid": 2019.35, "bb_lower": 2010.07}, {"date": "2025-09-01", "open": 2015.0, "high": 2025.0, "low": 2015.0, "close": 2015.0, "volume": 4069, "ma5": 2013.4, "ma20": 2018.85, "ma60": 2036.53, "ma120": null, "rsi": 41.3, "macd": -4.75, "macd_signal": -4.79, "macd_hist": 0.04, "bb_upper": 2027.93, "bb_mid": 2018.85, "bb_lower": 2009.77}, {"date": "2025-09-02", "open": 2015.0, "high": 2020.0, "low": 2010.0, "close": 2015.0, "volume": 10413, "ma5": 2013.4, "ma20": 2018.35, "ma60": 2035.62, "ma120": null, "rsi": 41.3, "macd": -4.57, "macd_signal": -4.74, "macd_hist": 0.17, "bb_upper": 2027.12, "bb_mid": 2018.35, "bb_lower": 2009.58}, {"date": "2025-09-03", "open": 2015.0, "high": 2015.0, "low": 2010.0, "close": 2015.0, "volume": 12350, "ma5": 2014.0, "ma20": 2018.1, "ma60": 2034.7, "ma120": null, "rsi": 41.3, "macd": -4.37, "macd_signal": -4.67, "macd_hist": 0.29, "bb_upper": 2026.95, "bb_mid": 2018.1, "bb_lower": 2009.25}, {"date": "2025-09-04", "open": 2025.0, "high": 2050.0, "low": 2020.0, "close": 2035.0, "volume": 14126, "ma5": 2019.0, "ma20": 2018.85, "ma60": 2034.03, "ma120": null, "rsi": 62.31, "macd": -2.58, "macd_signal": -4.25, "macd_hist": 1.67, "bb_upper": 2030.36, "bb_mid": 2018.85, "bb_lower": 2007.34}, {"date": "2025-09-05", "open": 2030.0, "high": 2030.0, "low": 2025.0, "close": 2030.0, "volume": 543, "ma5": 2022.0, "ma20": 2019.35, "ma60": 2033.45, "ma120": null, "rsi": 56.83, "macd": -1.54, "macd_signal": -3.71, "macd_hist": 2.17, "bb_upper": 2031.84, "bb_mid": 2019.35, "bb_lower": 2006.86}, {"date": "2025-09-08", "open": 2030.0, "high": 2030.0, "low": 2025.0, "close": 2025.0, "volume": 3942, "ma5": 2024.0, "ma20": 2020.1, "ma60": 2032.95, "ma120": null, "rsi": 51.92, "macd": -1.11, "macd_signal": -3.19, "macd_hist": 2.08, "bb_upper": 2032.05, "bb_mid": 2020.1, "bb_lower": 2008.15}, {"date": "2025-09-09", "open": 2025.0, "high": 2030.0, "low": 2020.0, "close": 2030.0, "volume": 2005, "ma5": 2027.0, "ma20": 2020.6, "ma60": 2032.37, "ma120": null, "rsi": 56.01, "macd": -0.36, "macd_signal": -2.62, "macd_hist": 2.26, "bb_upper": 2033.3, "bb_mid": 2020.6, "bb_lower": 2007.9}, {"date": "2025-09-10", "open": 2030.0, "high": 2030.0, "low": 2020.0, "close": 2025.0, "volume": 2299, "ma5": 2029.0, "ma20": 2020.85, "ma60": 2031.7, "ma120": null, "rsi": 51.31, "macd": -0.17, "macd_signal": -2.13, "macd_hist": 1.97, "bb_upper": 2033.69, "bb_mid": 2020.85, "bb_lower": 2008.01}, {"date": "2025-09-11", "open": 2025.0, "high": 2030.0, "low": 2020.0, "close": 2025.0, "volume": 12572, "ma5": 2027.0, "ma20": 2021.1, "ma60": 2031.03, "ma120": null, "rsi": 51.31, "macd": -0.01, "macd_signal": -1.71, "macd_hist": 1.69, "bb_upper": 2034.06, "bb_mid": 2021.1, "bb_lower": 2008.14}, {"date": "2025-09-12", "open": 2020.0, "high": 2030.0, "low": 2020.0, "close": 2020.0, "volume": 17410, "ma5": 2025.0, "ma20": 2020.85, "ma60": 2030.45, "ma120": null, "rsi": 46.75, "macd": -0.29, "macd_signal": -1.42, "macd_hist": 1.13, "bb_upper": 2033.69, "bb_mid": 2020.85, "bb_lower": 2008.01}, {"date": "2025-09-15", "open": 2020.0, "high": 2045.0, "low": 2020.0, "close": 2030.0, "volume": 21434, "ma5": 2026.0, "ma20": 2021.1, "ma60": 2030.12, "ma120": null, "rsi": 55.3, "macd": 0.29, "macd_signal": -1.08, "macd_hist": 1.37, "bb_upper": 2034.44, "bb_mid": 2021.1, "bb_lower": 2007.76}, {"date": "2025-09-16", "open": 2030.0, "high": 2040.0, "low": 2025.0, "close": 2030.0, "volume": 8751, "ma5": 2026.0, "ma20": 2021.6, "ma60": 2029.7, "ma120": null, "rsi": 55.3, "macd": 0.74, "macd_signal": -0.72, "macd_hist": 1.46, "bb_upper": 2035.48, "bb_mid": 2021.6, "bb_lower": 2007.72}, {"date": "2025-09-17", "open": 2025.0, "high": 2035.0, "low": 2025.0, "close": 2030.0, "volume": 4785, "ma5": 2027.0, "ma20": 2022.1, "ma60": 2029.45, "ma120": null, "rsi": 55.3, "macd": 1.09, "macd_signal": -0.35, "macd_hist": 1.45, "bb_upper": 2036.42, "bb_mid": 2022.1, "bb_lower": 2007.78}, {"date": "2025-09-18", "open": 2030.0, "high": 2032.0, "low": 2025.0, "close": 2030.0, "volume": 2968, "ma5": 2028.0, "ma20": 2022.35, "ma60": 2029.2, "ma120": null, "rsi": 55.3, "macd": 1.35, "macd_signal": -0.01, "macd_hist": 1.36, "bb_upper": 2037.04, "bb_mid": 2022.35, "bb_lower": 2007.66}, {"date": "2025-09-19", "open": 2025.0, "high": 2030.0, "low": 2025.0, "close": 2030.0, "volume": 173, "ma5": 2030.0, "ma20": 2022.85, "ma60": 2028.95, "ma120": null, "rsi": 55.3, "macd": 1.54, "macd_signal": 0.3, "macd_hist": 1.24, "bb_upper": 2037.86, "bb_mid": 2022.85, "bb_lower": 2007.84}, {"date": "2025-09-22", "open": 2030.0, "high": 2035.0, "low": 2020.0, "close": 2030.0, "volume": 2727, "ma5": 2030.0, "ma20": 2023.35, "ma60": 2028.53, "ma120": null, "rsi": 55.3, "macd": 1.67, "macd_signal": 0.57, "macd_hist": 1.1, "bb_upper": 2038.61, "bb_mid": 2023.35, "bb_lower": 2008.09}, {"date": "2025-09-23", "open": 2030.0, "high": 2035.0, "low": 2030.0, "close": 2035.0, "volume": 633, "ma5": 2031.0, "ma20": 2024.35, "ma60": 2028.12, "ma120": null, "rsi": 60.28, "macd": 2.15, "macd_signal": 0.89, "macd_hist": 1.26, "bb_upper": 2039.91, "bb_mid": 2024.35, "bb_lower": 2008.79}, {"date": "2025-09-24", "open": 2035.0, "high": 2035.0, "low": 2030.0, "close": 2035.0, "volume": 643, "ma5": 2032.0, "ma20": 2025.5, "ma60": 2027.7, "ma120": null, "rsi": 60.28, "macd": 2.5, "macd_signal": 1.21, "macd_hist": 1.29, "bb_upper": 2040.63, "bb_mid": 2025.5, "bb_lower": 2010.37}, {"date": "2025-09-25", "open": 2025.0, "high": 2035.0, "low": 2025.0, "close": 2035.0, "volume": 2005, "ma5": 2033.0, "ma20": 2026.75, "ma60": 2027.37, "ma120": null, "rsi": 60.28, "macd": 2.75, "macd_signal": 1.52, "macd_hist": 1.23, "bb_upper": 2040.63, "bb_mid": 2026.75, "bb_lower": 2012.87}, {"date": "2025-09-26", "open": 2035.0, "high": 2045.0, "low": 2035.0, "close": 2040.0, "volume": 15901, "ma5": 2035.0, "ma20": 2028.0, "ma60": 2027.12, "ma120": null, "rsi": 65.12, "macd": 3.31, "macd_signal": 1.88, "macd_hist": 1.43, "bb_upper": 2041.93, "bb_mid": 2028.0, "bb_lower": 2014.07}, {"date": "2025-09-29", "open": 2045.0, "high": 2060.0, "low": 2035.0, "close": 2045.0, "volume": 24064, "ma5": 2038.0, "ma20": 2029.5, "ma60": 2027.03, "ma120": null, "rsi": 69.18, "macd": 4.11, "macd_signal": 2.32, "macd_hist": 1.79, "bb_upper": 2043.96, "bb_mid": 2029.5, "bb_lower": 2015.04}, {"date": "2025-09-30", "open": 2035.0, "high": 2050.0, "low": 2035.0, "close": 2040.0, "volume": 2875, "ma5": 2039.0, "ma20": 2030.75, "ma60": 2026.95, "ma120": null, "rsi": 61.48, "macd": 4.29, "macd_signal": 2.72, "macd_hist": 1.58, "bb_upper": 2044.27, "bb_mid": 2030.75, "bb_lower": 2017.23}, {"date": "2025-10-01", "open": 2045.0, "high": 2060.0, "low": 2045.0, "close": 2050.0, "volume": 2488, "ma5": 2042.0, "ma20": 2032.5, "ma60": 2027.12, "ma120": null, "rsi": 68.93, "macd": 5.18, "macd_signal": 3.21, "macd_hist": 1.97, "bb_upper": 2046.46, "bb_mid": 2032.5, "bb_lower": 2018.54}, {"date": "2025-10-02", "open": 2050.0, "high": 2075.0, "low": 2045.0, "close": 2045.0, "volume": 6623, "ma5": 2044.0, "ma20": 2033.0, "ma60": 2027.28, "ma120": null, "rsi": 62.43, "macd": 5.42, "macd_signal": 3.65, "macd_hist": 1.77, "bb_upper": 2047.97, "bb_mid": 2033.0, "bb_lower": 2018.03}, {"date": "2025-10-10", "open": 2045.0, "high": 2045.0, "low": 2035.0, "close": 2045.0, "volume": 27621, "ma5": 2045.0, "ma20": 2033.75, "ma60": 2027.53, "ma120": null, "rsi": 62.43, "macd": 5.55, "macd_signal": 4.03, "macd_hist": 1.52, "bb_upper": 2049.52, "bb_mid": 2033.75, "bb_lower": 2017.98}, {"date": "2025-10-13", "open": 2035.0, "high": 2045.0, "low": 2035.0, "close": 2045.0, "volume": 1497, "ma5": 2045.0, "ma20": 2034.75, "ma60": 2027.87, "ma120": null, "rsi": 62.43, "macd": 5.59, "macd_signal": 4.34, "macd_hist": 1.24, "bb_upper": 2050.71, "bb_mid": 2034.75, "bb_lower": 2018.79}, {"date": "2025-10-14", "open": 2045.0, "high": 2045.0, "low": 2040.0, "close": 2040.0, "volume": 1477, "ma5": 2045.0, "ma20": 2035.25, "ma60": 2028.03, "ma120": null, "rsi": 55.86, "macd": 5.15, "macd_signal": 4.51, "macd_hist": 0.65, "bb_upper": 2051.21, "bb_mid": 2035.25, "bb_lower": 2019.29}, {"date": "2025-10-15", "open": 2040.0, "high": 2050.0, "low": 2040.0, "close": 2050.0, "volume": 27155, "ma5": 2045.0, "ma20": 2036.5, "ma60": 2028.45, "ma120": null, "rsi": 64.02, "macd": 5.55, "macd_signal": 4.71, "macd_hist": 0.84, "bb_upper": 2052.96, "bb_mid": 2036.5, "bb_lower": 2020.04}, {"date": "2025-10-16", "open": 2040.0, "high": 2050.0, "low": 2040.0, "close": 2050.0, "volume": 3352, "ma5": 2046.0, "ma20": 2037.75, "ma60": 2028.78, "ma120": null, "rsi": 64.02, "macd": 5.8, "macd_signal": 4.93, "macd_hist": 0.87, "bb_upper": 2054.33, "bb_mid": 2037.75, "bb_lower": 2021.17}, {"date": "2025-10-17", "open": 2040.0, "high": 2050.0, "low": 2040.0, "close": 2050.0, "volume": 328, "ma5": 2047.0, "ma20": 2039.25, "ma60": 2029.03, "ma120": null, "rsi": 64.02, "macd": 5.93, "macd_signal": 5.13, "macd_hist": 0.8, "bb_upper": 2054.51, "bb_mid": 2039.25, "bb_lower": 2023.99}, {"date": "2025-10-20", "open": 2040.0, "high": 2050.0, "low": 2040.0, "close": 2050.0, "volume": 11158, "ma5": 2048.0, "ma20": 2040.25, "ma60": 2029.28, "ma120": null, "rsi": 64.02, "macd": 5.96, "macd_signal": 5.3, "macd_hist": 0.67, "bb_upper": 2055.57, "bb_mid": 2040.25, "bb_lower": 2024.93}, {"date": "2025-10-21", "open": 2040.0, "high": 2055.0, "low": 2040.0, "close": 2055.0, "volume": 20473, "ma5": 2051.0, "ma20": 2041.5, "ma60": 2029.62, "ma120": null, "rsi": 68.0, "macd": 6.32, "macd_signal": 5.5, "macd_hist": 0.82, "bb_upper": 2057.34, "bb_mid": 2041.5, "bb_lower": 2025.66}, {"date": "2025-10-22", "open": 2055.0, "high": 2055.0, "low": 2040.0, "close": 2045.0, "volume": 4061, "ma5": 2050.0, "ma20": 2042.25, "ma60": 2029.7, "ma120": null, "rsi": 54.92, "macd": 5.73, "macd_signal": 5.55, "macd_hist": 0.18, "bb_upper": 2057.24, "bb_mid": 2042.25, "bb_lower": 2027.26}, {"date": "2025-10-23", "open": 2045.0, "high": 2050.0, "low": 2045.0, "close": 2050.0, "volume": 2218, "ma5": 2050.0, "ma20": 2043.25, "ma60": 2029.87, "ma120": null, "rsi": 59.15, "macd": 5.6, "macd_signal": 5.56, "macd_hist": 0.04, "bb_upper": 2057.49, "bb_mid": 2043.25, "bb_lower": 2029.01}, {"date": "2025-10-24", "open": 2045.0, "high": 2045.0, "low": 2035.0, "close": 2040.0, "volume": 10509, "ma5": 2048.0, "ma20": 2043.75, "ma60": 2029.87, "ma120": null, "rsi": 49.2, "macd": 4.64, "macd_signal": 5.37, "macd_hist": -0.74, "bb_upper": 2056.74, "bb_mid": 2043.75, "bb_lower": 2030.76}, {"date": "2025-10-27", "open": 2035.0, "high": 2050.0, "low": 2035.0, "close": 2045.0, "volume": 1154, "ma5": 2047.0, "ma20": 2044.5, "ma60": 2030.2, "ma120": null, "rsi": 53.42, "macd": 4.23, "macd_signal": 5.15, "macd_hist": -0.91, "bb_upper": 2055.86, "bb_mid": 2044.5, "bb_lower": 2033.14}, {"date": "2025-10-28", "open": 2040.0, "high": 2055.0, "low": 2040.0, "close": 2050.0, "volume": 6191, "ma5": 2046.0, "ma20": 2045.25, "ma60": 2030.45, "ma120": null, "rsi": 57.24, "macd": 4.26, "macd_signal": 4.97, "macd_hist": -0.71, "bb_upper": 2055.96, "bb_mid": 2045.25, "bb_lower": 2034.54}, {"date": "2025-10-29", "open": 2050.0, "high": 2060.0, "low": 2050.0, "close": 2050.0, "volume": 2122, "ma5": 2047.0, "ma20": 2046.0, "ma60": 2030.7, "ma120": 2039.85, "rsi": 57.24, "macd": 4.24, "macd_signal": 4.82, "macd_hist": -0.58, "bb_upper": 2055.8, "bb_mid": 2046.0, "bb_lower": 2036.2}, {"date": "2025-10-30", "open": 2050.0, "high": 2050.0, "low": 2035.0, "close": 2045.0, "volume": 5144, "ma5": 2046.0, "ma20": 2046.5, "ma60": 2031.03, "ma120": 2039.89, "rsi": 52.27, "macd": 3.77, "macd_signal": 4.61, "macd_hist": -0.84, "bb_upper": 2054.93, "bb_mid": 2046.5, "bb_lower": 2038.07}, {"date": "2025-10-31", "open": 2045.0, "high": 2050.0, "low": 2010.0, "close": 2050.0, "volume": 36583, "ma5": 2048.0, "ma20": 2047.0, "ma60": 2031.45, "ma120": 2039.89, "rsi": 56.35, "macd": 3.76, "macd_signal": 4.44, "macd_hist": -0.68, "bb_upper": 2055.0, "bb_mid": 2047.0, "bb_lower": 2039.0}, {"date": "2025-11-03", "open": 2040.0, "high": 2055.0, "low": 2040.0, "close": 2040.0, "volume": 12928, "ma5": 2047.0, "ma20": 2046.75, "ma60": 2031.7, "ma120": 2039.89, "rsi": 47.58, "macd": 2.91, "macd_signal": 4.14, "macd_hist": -1.22, "bb_upper": 2055.28, "bb_mid": 2046.75, "bb_lower": 2038.22}, {"date": "2025-11-04", "open": 2045.0, "high": 2050.0, "low": 2040.0, "close": 2050.0, "volume": 14608, "ma5": 2047.0, "ma20": 2047.25, "ma60": 2032.12, "ma120": 2039.98, "rsi": 55.11, "macd": 3.01, "macd_signal": 3.91, "macd_hist": -0.9, "bb_upper": 2055.3, "bb_mid": 2047.25, "bb_lower": 2039.2}, {"date": "2025-11-05", "open": 2040.0, "high": 2055.0, "low": 2005.0, "close": 2045.0, "volume": 17286, "ma5": 2046.0, "ma20": 2047.0, "ma60": 2032.53, "ma120": 2040.02, "rsi": 51.15, "macd": 2.66, "macd_signal": 3.66, "macd_hist": -1.0, "bb_upper": 2055.0, "bb_mid": 2047.0, "bb_lower": 2039.0}, {"date": "2025-11-06", "open": 2045.0, "high": 2050.0, "low": 2035.0, "close": 2050.0, "volume": 92179, "ma5": 2047.0, "ma20": 2047.25, "ma60": 2033.03, "ma120": 2040.1, "rsi": 54.66, "macd": 2.75, "macd_signal": 3.48, "macd_hist": -0.73, "bb_upper": 2055.3, "bb_mid": 2047.25, "bb_lower": 2039.2}, {"date": "2025-11-07", "open": 2040.0, "high": 2055.0, "low": 2040.0, "close": 2050.0, "volume": 4554, "ma5": 2047.0, "ma20": 2047.5, "ma60": 2033.53, "ma120": 2040.06, "rsi": 54.66, "macd": 2.79, "macd_signal": 3.34, "macd_hist": -0.55, "bb_upper": 2055.56, "bb_mid": 2047.5, "bb_lower": 2039.44}, {"date": "2025-11-10", "open": 2050.0, "high": 2050.0, "low": 2040.0, "close": 2040.0, "volume": 591, "ma5": 2047.0, "ma20": 2047.25, "ma60": 2034.03, "ma120": 2039.93, "rsi": 46.86, "macd": 1.99, "macd_signal": 3.07, "macd_hist": -1.08, "bb_upper": 2055.9, "bb_mid": 2047.25, "bb_lower": 2038.6}, {"date": "2025-11-11", "open": 2045.0, "high": 2045.0, "low": 2035.0, "close": 2040.0, "volume": 971, "ma5": 2045.0, "ma20": 2047.25, "ma60": 2034.37, "ma120": 2039.77, "rsi": 46.86, "macd": 1.34, "macd_signal": 2.73, "macd_hist": -1.38, "bb_upper": 2055.9, "bb_mid": 2047.25, "bb_lower": 2038.6}, {"date": "2025-11-12", "open": 2040.0, "high": 2040.0, "low": 2030.0, "close": 2030.0, "volume": 12775, "ma5": 2042.0, "ma20": 2046.25, "ma60": 2034.53, "ma120": 2039.56, "rsi": 40.21, "macd": 0.02, "macd_signal": 2.19, "macd_hist": -2.16, "bb_upper": 2057.6, "bb_mid": 2046.25, "bb_lower": 2034.9}, {"date": "2025-11-13", "open": 2030.0, "high": 2035.0, "low": 2025.0, "close": 2030.0, "volume": 37810, "ma5": 2038.0, "ma20": 2045.25, "ma60": 2034.7, "ma120": 2039.31, "rsi": 40.21, "macd": -1.01, "macd_signal": 1.55, "macd_hist": -2.56, "bb_upper": 2058.47, "bb_mid": 2045.25, "bb_lower": 2032.03}, {"date": "2025-11-14", "open": 2025.0, "high": 2030.0, "low": 2025.0, "close": 2030.0, "volume": 719, "ma5": 2034.0, "ma20": 2044.25, "ma60": 2034.78, "ma120": 2039.06, "rsi": 40.21, "macd": -1.81, "macd_signal": 0.87, "macd_hist": -2.69, "bb_upper": 2058.84, "bb_mid": 2044.25, "bb_lower": 2029.66}, {"date": "2025-11-17", "open": 2030.0, "high": 2035.0, "low": 2025.0, "close": 2035.0, "volume": 1367, "ma5": 2033.0, "ma20": 2043.5, "ma60": 2034.95, "ma120": 2038.93, "rsi": 45.08, "macd": -2.02, "macd_signal": 0.3, "macd_hist": -2.31, "bb_upper": 2058.37, "bb_mid": 2043.5, "bb_lower": 2028.63}, {"date": "2025-11-18", "open": 2035.0, "high": 2035.0, "low": 2035.0, "close": 2035.0, "volume": 189, "ma5": 2032.0, "ma20": 2042.5, "ma60": 2035.2, "ma120": 2038.81, "rsi": 45.08, "macd": -2.16, "macd_signal": -0.2, "macd_hist": -1.96, "bb_upper": 2056.82, "bb_mid": 2042.5, "bb_lower": 2028.18}, {"date": "2025-11-19", "open": 2030.0, "high": 2035.0, "low": 2025.0, "close": 2035.0, "volume": 878, "ma5": 2033.0, "ma20": 2042.0, "ma60": 2035.45, "ma120": 2038.68, "rsi": 45.08, "macd": -2.24, "macd_signal": -0.6, "macd_hist": -1.64, "bb_upper": 2056.63, "bb_mid": 2042.0, "bb_lower": 2027.37}, {"date": "2025-11-20", "open": 2030.0, "high": 2035.0, "low": 2027.0, "close": 2030.0, "volume": 685, "ma5": 2033.0, "ma20": 2041.0, "ma60": 2035.53, "ma120": 2038.43, "rsi": 40.92, "macd": -2.68, "macd_signal": -1.02, "macd_hist": -1.66, "bb_upper": 2056.03, "bb_mid": 2041.0, "bb_lower": 2025.97}, {"date": "2025-11-21", "open": 2030.0, "high": 2035.0, "low": 2030.0, "close": 2035.0, "volume": 589, "ma5": 2034.0, "ma20": 2040.75, "ma60": 2035.78, "ma120": 2038.31, "rsi": 46.26, "macd": -2.6, "macd_signal": -1.34, "macd_hist": -1.26, "bb_upper": 2056.01, "bb_mid": 2040.75, "bb_lower": 2025.49}, {"date": "2025-11-24", "open": 2025.0, "high": 2035.0, "low": 2020.0, "close": 2030.0, "volume": 8231, "ma5": 2033.0, "ma20": 2040.0, "ma60": 2035.95, "ma120": 2038.02, "rsi": 42.15, "macd": -2.9, "macd_signal": -1.65, "macd_hist": -1.25, "bb_upper": 2055.81, "bb_mid": 2040.0, "bb_lower": 2024.19}, {"date": "2025-11-25", "open": 2025.0, "high": 2030.0, "low": 2025.0, "close": 2030.0, "volume": 85, "ma5": 2032.0, "ma20": 2039.0, "ma60": 2036.2, "ma120": 2037.77, "rsi": 42.15, "macd": -3.1, "macd_signal": -1.94, "macd_hist": -1.16, "bb_upper": 2054.68, "bb_mid": 2039.0, "bb_lower": 2023.32}, {"date": "2025-11-26", "open": 2030.0, "high": 2040.0, "low": 2030.0, "close": 2040.0, "volume": 272, "ma5": 2033.0, "ma20": 2038.5, "ma60": 2036.67, "ma120": 2037.64, "rsi": 52.03, "macd": -2.43, "macd_signal": -2.04, "macd_hist": -0.39, "bb_upper": 2053.37, "bb_mid": 2038.5, "bb_lower": 2023.63}, {"date": "2025-11-27", "open": 2030.0, "high": 2055.0, "low": 2025.0, "close": 2050.0, "volume": 21857, "ma5": 2037.0, "ma20": 2038.75, "ma60": 2037.33, "ma120": 2037.6, "rsi": 59.48, "macd": -1.08, "macd_signal": -1.85, "macd_hist": 0.77, "bb_upper": 2054.2, "bb_mid": 2038.75, "bb_lower": 2023.3}, {"date": "2025-11-28", "open": 2040.0, "high": 2050.0, "low": 2035.0, "close": 2050.0, "volume": 726, "ma5": 2040.0, "ma20": 2038.75, "ma60": 2037.92, "ma120": 2037.56, "rsi": 59.48, "macd": -0.0, "macd_signal": -1.48, "macd_hist": 1.47, "bb_upper": 2054.2, "bb_mid": 2038.75, "bb_lower": 2023.3}, {"date": "2025-12-01", "open": 2050.0, "high": 2055.0, "low": 2035.0, "close": 2050.0, "volume": 34132, "ma5": 2044.0, "ma20": 2039.25, "ma60": 2038.5, "ma120": 2037.52, "rsi": 59.48, "macd": 0.84, "macd_signal": -1.01, "macd_hist": 1.85, "bb_upper": 2055.46, "bb_mid": 2039.25, "bb_lower": 2023.04}, {"date": "2025-12-02", "open": 2050.0, "high": 2080.0, "low": 2045.0, "close": 2050.0, "volume": 20650, "ma5": 2048.0, "ma20": 2039.25, "ma60": 2039.08, "ma120": 2037.35, "rsi": 59.48, "macd": 1.48, "macd_signal": -0.51, "macd_hist": 2.0, "bb_upper": 2055.46, "bb_mid": 2039.25, "bb_lower": 2023.04}, {"date": "2025-12-03", "open": 2045.0, "high": 2105.0, "low": 2040.0, "close": 2070.0, "volume": 27147, "ma5": 2054.0, "ma20": 2040.5, "ma60": 2040.0, "ma120": 2037.35, "rsi": 71.42, "macd": 3.57, "macd_signal": 0.3, "macd_hist": 3.27, "bb_upper": 2061.45, "bb_mid": 2040.5, "bb_lower": 2019.55}, {"date": "2025-12-04", "open": 2070.0, "high": 2100.0, "low": 2055.0, "close": 2075.0, "volume": 22192, "ma5": 2059.0, "ma20": 2041.75, "ma60": 2040.67, "ma120": 2037.35, "rsi": 73.52, "macd": 5.56, "macd_signal": 1.35, "macd_hist": 4.21, "bb_upper": 2067.3, "bb_mid": 2041.75, "bb_lower": 2016.2}, {"date": "2025-12-05", "open": 2070.0, "high": 2080.0, "low": 2065.0, "close": 2075.0, "volume": 15441, "ma5": 2064.0, "ma20": 2043.0, "ma60": 2041.42, "ma120": 2037.43, "rsi": 73.52, "macd": 7.06, "macd_signal": 2.5, "macd_hist": 4.57, "bb_upper": 2072.22, "bb_mid": 2043.0, "bb_lower": 2013.78}, {"date": "2025-12-08", "open": 2075.0, "high": 2085.0, "low": 2065.0, "close": 2085.0, "volume": 3459, "ma5": 2071.0, "ma20": 2045.25, "ma60": 2042.42, "ma120": 2037.68, "rsi": 77.38, "macd": 8.95, "macd_signal": 3.79, "macd_hist": 5.17, "bb_upper": 2079.67, "bb_mid": 2045.25, "bb_lower": 2010.83}, {"date": "2025-12-09", "open": 2085.0, "high": 2085.0, "low": 2075.0, "close": 2075.0, "volume": 1073, "ma5": 2076.0, "ma20": 2047.0, "ma60": 2043.17, "ma120": 2037.77, "rsi": 66.88, "macd": 9.53, "macd_signal": 4.94, "macd_hist": 4.6, "bb_upper": 2083.66, "bb_mid": 2047.0, "bb_lower": 2010.34}, {"date": "2025-12-10", "open": 2075.0, "high": 2075.0, "low": 2065.0, "close": 2070.0, "volume": 7491, "ma5": 2076.0, "ma20": 2049.0, "ma60": 2043.92, "ma120": 2037.81, "rsi": 62.33, "macd": 9.48, "macd_signal": 5.85, "macd_hist": 3.64, "bb_upper": 2086.09, "bb_mid": 2049.0, "bb_lower": 2011.91}, {"date": "2025-12-11", "open": 2060.0, "high": 2075.0, "low": 2060.0, "close": 2065.0, "volume": 15383, "ma5": 2074.0, "ma20": 2050.75, "ma60": 2044.58, "ma120": 2037.81, "rsi": 58.08, "macd": 8.94, "macd_signal": 6.46, "macd_hist": 2.47, "bb_upper": 2087.39, "bb_mid": 2050.75, "bb_lower": 2014.11}, {"date": "2025-12-12", "open": 2060.0, "high": 2060.0, "low": 2040.0, "close": 2055.0, "volume": 13379, "ma5": 2070.0, "ma20": 2052.0, "ma60": 2045.17, "ma120": 2037.81, "rsi": 50.63, "macd": 7.61, "macd_signal": 6.69, "macd_hist": 0.91, "bb_upper": 2087.41, "bb_mid": 2052.0, "bb_lower": 2016.59}, {"date": "2025-12-15", "open": 2050.0, "high": 2055.0, "low": 2030.0, "close": 2030.0, "volume": 18737, "ma5": 2059.0, "ma20": 2051.75, "ma60": 2045.17, "ma120": 2037.64, "rsi": 37.64, "macd": 4.49, "macd_signal": 6.25, "macd_hist": -1.77, "bb_upper": 2087.7, "bb_mid": 2051.75, "bb_lower": 2015.8}, {"date": "2025-12-16", "open": 2025.0, "high": 2040.0, "low": 2025.0, "close": 2030.0, "volume": 2078, "ma5": 2050.0, "ma20": 2051.5, "ma60": 2045.17, "ma120": 2037.43, "rsi": 37.64, "macd": 1.99, "macd_signal": 5.4, "macd_hist": -3.41, "bb_upper": 2087.98, "bb_mid": 2051.5, "bb_lower": 2015.02}, {"date": "2025-12-17", "open": 2030.0, "high": 2050.0, "low": 2030.0, "close": 2040.0, "volume": 21571, "ma5": 2044.0, "ma20": 2051.75, "ma60": 2045.33, "ma120": 2037.39, "rsi": 44.27, "macd": 0.81, "macd_signal": 4.48, "macd_hist": -3.67, "bb_upper": 2087.84, "bb_mid": 2051.75, "bb_lower": 2015.66}, {"date": "2025-12-18", "open": 2040.0, "high": 2055.0, "low": 2040.0, "close": 2040.0, "volume": 126, "ma5": 2039.0, "ma20": 2052.25, "ma60": 2045.5, "ma120": 2037.35, "rsi": 44.27, "macd": -0.13, "macd_signal": 3.56, "macd_hist": -3.69, "bb_upper": 2087.39, "bb_mid": 2052.25, "bb_lower": 2017.11}, {"date": "2025-12-19", "open": 2035.0, "high": 2040.0, "low": 2035.0, "close": 2035.0, "volume": 855, "ma5": 2035.0, "ma20": 2052.25, "ma60": 2045.58, "ma120": 2037.27, "rsi": 41.7, "macd": -1.26, "macd_signal": 2.6, "macd_hist": -3.85, "bb_upper": 2087.39, "bb_mid": 2052.25, "bb_lower": 2017.11}, {"date": "2025-12-22", "open": 2035.0, "high": 2045.0, "low": 2035.0, "close": 2040.0, "volume": 13610, "ma5": 2037.0, "ma20": 2052.75, "ma60": 2045.75, "ma120": 2037.14, "rsi": 45.13, "macd": -1.73, "macd_signal": 1.73, "macd_hist": -3.46, "bb_upper": 2086.88, "bb_mid": 2052.75, "bb_lower": 2018.62}, {"date": "2025-12-23", "open": 2040.0, "high": 2050.0, "low": 2040.0, "close": 2045.0, "volume": 1372, "ma5": 2040.0, "ma20": 2053.5, "ma60": 2045.92, "ma120": 2037.02, "rsi": 48.41, "macd": -1.68, "macd_signal": 1.05, "macd_hist": -2.73, "bb_upper": 2086.23, "bb_mid": 2053.5, "bb_lower": 2020.77}, {"date": "2025-12-24", "open": 2045.0, "high": 2045.0, "low": 2040.0, "close": 2040.0, "volume": 723, "ma5": 2040.0, "ma20": 2053.5, "ma60": 2046.0, "ma120": 2036.85, "rsi": 45.49, "macd": -2.02, "macd_signal": 0.43, "macd_hist": -2.46, "bb_upper": 2086.23, "bb_mid": 2053.5, "bb_lower": 2020.77}, {"date": "2025-12-26", "open": 2040.0, "high": 2045.0, "low": 2040.0, "close": 2045.0, "volume": 183, "ma5": 2041.0, "ma20": 2053.25, "ma60": 2046.17, "ma120": 2036.77, "rsi": 48.81, "macd": -1.87, "macd_signal": -0.03, "macd_hist": -1.84, "bb_upper": 2086.16, "bb_mid": 2053.25, "bb_lower": 2020.34}, {"date": "2025-12-29", "open": 2050.0, "high": 2055.0, "low": 2045.0, "close": 2045.0, "volume": 1235, "ma5": 2043.0, "ma20": 2053.0, "ma60": 2046.25, "ma120": 2036.68, "rsi": 48.81, "macd": -1.73, "macd_signal": -0.37, "macd_hist": -1.36, "bb_upper": 2086.08, "bb_mid": 2053.0, "bb_lower": 2019.92}, {"date": "2025-12-30", "open": 2045.0, "high": 2055.0, "low": 2045.0, "close": 2050.0, "volume": 2069, "ma5": 2045.0, "ma20": 2053.0, "ma60": 2046.33, "ma120": 2036.68, "rsi": 52.19, "macd": -1.2, "macd_signal": -0.53, "macd_hist": -0.66, "bb_upper": 2086.08, "bb_mid": 2053.0, "bb_lower": 2019.92}, {"date": "2026-01-02", "open": 2050.0, "high": 2050.0, "low": 2040.0, "close": 2045.0, "volume": 1651, "ma5": 2045.0, "ma20": 2052.75, "ma60": 2046.42, "ma120": 2036.68, "rsi": 48.73, "macd": -1.17, "macd_signal": -0.66, "macd_hist": -0.51, "bb_upper": 2085.99, "bb_mid": 2052.75, "bb_lower": 2019.51}, {"date": "2026-01-05", "open": 2045.0, "high": 2045.0, "low": 2040.0, "close": 2042.0, "volume": 1606, "ma5": 2045.4, "ma20": 2051.35, "ma60": 2046.28, "ma120": 2036.7, "rsi": 46.72, "macd": -1.37, "macd_signal": -0.8, "macd_hist": -0.57, "bb_upper": 2083.92, "bb_mid": 2051.35, "bb_lower": 2018.78}, {"date": "2026-01-06", "open": 2045.0, "high": 2045.0, "low": 2040.0, "close": 2045.0, "volume": 16194, "ma5": 2045.4, "ma20": 2049.85, "ma60": 2046.28, "ma120": 2036.78, "rsi": 48.98, "macd": -1.27, "macd_signal": -0.89, "macd_hist": -0.38, "bb_upper": 2080.63, "bb_mid": 2049.85, "bb_lower": 2019.07}, {"date": "2026-01-07", "open": 2040.0, "high": 2045.0, "low": 2040.0, "close": 2045.0, "volume": 3698, "ma5": 2045.4, "ma20": 2048.35, "ma60": 2046.28, "ma120": 2036.91, "rsi": 48.98, "macd": -1.18, "macd_signal": -0.95, "macd_hist": -0.23, "bb_upper": 2076.93, "bb_mid": 2048.35, "bb_lower": 2019.77}, {"date": "2026-01-08", "open": 2050.0, "high": 2050.0, "low": 2040.0, "close": 2050.0, "volume": 643, "ma5": 2045.4, "ma20": 2046.6, "ma60": 2046.37, "ma120": 2037.12, "rsi": 52.85, "macd": -0.7, "macd_signal": -0.9, "macd_hist": 0.2, "bb_upper": 2069.76, "bb_mid": 2046.6, "bb_lower": 2023.44}, {"date": "2026-01-09", "open": 2045.0, "high": 2055.0, "low": 2045.0, "close": 2055.0, "volume": 6525, "ma5": 2047.4, "ma20": 2045.6, "ma60": 2046.62, "ma120": 2037.32, "rsi": 56.41, "macd": 0.09, "macd_signal": -0.7, "macd_hist": 0.79, "bb_upper": 2065.23, "bb_mid": 2045.6, "bb_lower": 2025.97}, {"date": "2026-01-12", "open": 2055.0, "high": 2060.0, "low": 2055.0, "close": 2060.0, "volume": 3817, "ma5": 2051.0, "ma20": 2045.1, "ma60": 2046.78, "ma120": 2037.62, "rsi": 59.69, "macd": 1.1, "macd_signal": -0.34, "macd_hist": 1.44, "bb_upper": 2062.61, "bb_mid": 2045.1, "bb_lower": 2027.59}, {"date": "2026-01-13", "open": 2055.0, "high": 2060.0, "low": 2055.0, "close": 2055.0, "volume": 2675, "ma5": 2053.0, "ma20": 2044.6, "ma60": 2046.87, "ma120": 2037.82, "rsi": 55.22, "macd": 1.48, "macd_signal": 0.02, "macd_hist": 1.46, "bb_upper": 2060.29, "bb_mid": 2044.6, "bb_lower": 2028.91}, {"date": "2026-01-14", "open": 2050.0, "high": 2055.0, "low": 2050.0, "close": 2055.0, "volume": 20926, "ma5": 2055.0, "ma20": 2044.6, "ma60": 2046.95, "ma120": 2037.99, "rsi": 55.22, "macd": 1.76, "macd_signal": 0.37, "macd_hist": 1.39, "bb_upper": 2060.29, "bb_mid": 2044.6, "bb_lower": 2028.91}, {"date": "2026-01-15", "open": 2050.0, "high": 2065.0, "low": 2050.0, "close": 2060.0, "volume": 755, "ma5": 2057.0, "ma20": 2046.1, "ma60": 2047.12, "ma120": 2038.2, "rsi": 58.8, "macd": 2.36, "macd_signal": 0.77, "macd_hist": 1.6, "bb_upper": 2061.66, "bb_mid": 2046.1, "bb_lower": 2030.54}, {"date": "2026-01-16", "open": 2060.0, "high": 2065.0, "low": 2060.0, "close": 2060.0, "volume": 2002, "ma5": 2058.0, "ma20": 2047.6, "ma60": 2047.2, "ma120": 2038.41, "rsi": 58.8, "macd": 2.81, "macd_signal": 1.18, "macd_hist": 1.63, "bb_upper": 2062.42, "bb_mid": 2047.6, "bb_lower": 2032.78}, {"date": "2026-01-19", "open": 2060.0, "high": 2070.0, "low": 2055.0, "close": 2060.0, "volume": 2962, "ma5": 2058.0, "ma20": 2048.6, "ma60": 2047.45, "ma120": 2038.58, "rsi": 58.8, "macd": 3.12, "macd_signal": 1.57, "macd_hist": 1.56, "bb_upper": 2063.93, "bb_mid": 2048.6, "bb_lower": 2033.27}, {"date": "2026-01-20", "open": 2070.0, "high": 2075.0, "low": 2060.0, "close": 2075.0, "volume": 20370, "ma5": 2062.0, "ma20": 2050.35, "ma60": 2047.87, "ma120": 2038.87, "rsi": 68.29, "macd": 4.53, "macd_signal": 2.16, "macd_hist": 2.37, "bb_upper": 2068.99, "bb_mid": 2050.35, "bb_lower": 2031.71}, {"date": "2026-01-21", "open": 2085.0, "high": 2085.0, "low": 2060.0, "close": 2065.0, "volume": 6423, "ma5": 2064.0, "ma20": 2051.85, "ma60": 2048.28, "ma120": 2039.08, "rsi": 58.6, "macd": 4.78, "macd_signal": 2.68, "macd_hist": 2.1, "bb_upper": 2070.13, "bb_mid": 2051.85, "bb_lower": 2033.57}, {"date": "2026-01-22", "open": 2065.0, "high": 2070.0, "low": 2060.0, "close": 2060.0, "volume": 9674, "ma5": 2064.0, "ma20": 2052.85, "ma60": 2048.53, "ma120": 2039.37, "rsi": 54.44, "macd": 4.53, "macd_signal": 3.05, "macd_hist": 1.48, "bb_upper": 2070.61, "bb_mid": 2052.85, "bb_lower": 2035.09}, {"date": "2026-01-23", "open": 2060.0, "high": 2080.0, "low": 2060.0, "close": 2070.0, "volume": 2799, "ma5": 2066.0, "ma20": 2054.1, "ma60": 2048.87, "ma120": 2039.66, "rsi": 60.48, "macd": 5.08, "macd_signal": 3.46, "macd_hist": 1.62, "bb_upper": 2072.96, "bb_mid": 2054.1, "bb_lower": 2035.24}, {"date": "2026-01-26", "open": 2065.0, "high": 2075.0, "low": 2060.0, "close": 2075.0, "volume": 4467, "ma5": 2069.0, "ma20": 2055.85, "ma60": 2049.28, "ma120": 2039.99, "rsi": 63.12, "macd": 5.85, "macd_signal": 3.94, "macd_hist": 1.91, "bb_upper": 2075.62, "bb_mid": 2055.85, "bb_lower": 2036.08}, {"date": "2026-01-27", "open": 2075.0, "high": 2075.0, "low": 2070.0, "close": 2070.0, "volume": 3444, "ma5": 2068.0, "ma20": 2057.1, "ma60": 2049.7, "ma120": 2040.37, "rsi": 58.89, "macd": 5.98, "macd_signal": 4.34, "macd_hist": 1.64, "bb_upper": 2077.13, "bb_mid": 2057.1, "bb_lower": 2037.07}, {"date": "2026-01-28", "open": 2075.0, "high": 2090.0, "low": 2075.0, "close": 2075.0, "volume": 5277, "ma5": 2070.0, "ma20": 2058.6, "ma60": 2050.12, "ma120": 2040.78, "rsi": 61.65, "macd": 6.42, "macd_signal": 4.76, "macd_hist": 1.66, "bb_upper": 2079.26, "bb_mid": 2058.6, "bb_lower": 2037.94}, {"date": "2026-01-29", "open": 2070.0, "high": 2075.0, "low": 2055.0, "close": 2070.0, "volume": 7292, "ma5": 2072.0, "ma20": 2059.6, "ma60": 2050.62, "ma120": 2041.16, "rsi": 57.49, "macd": 6.29, "macd_signal": 5.07, "macd_hist": 1.23, "bb_upper": 2080.44, "bb_mid": 2059.6, "bb_lower": 2038.76}, {"date": "2026-01-30", "open": 2060.0, "high": 2075.0, "low": 2045.0, "close": 2050.0, "volume": 40036, "ma5": 2068.0, "ma20": 2059.85, "ma60": 2050.62, "ma120": 2041.37, "rsi": 44.53, "macd": 4.52, "macd_signal": 4.96, "macd_hist": -0.43, "bb_upper": 2080.09, "bb_mid": 2059.85, "bb_lower": 2039.61}, {"date": "2026-02-02", "open": 2050.0, "high": 2055.0, "low": 2050.0, "close": 2055.0, "volume": 1551, "ma5": 2064.0, "ma20": 2060.5, "ma60": 2050.78, "ma120": 2041.66, "rsi": 47.7, "macd": 3.49, "macd_signal": 4.66, "macd_hist": -1.18, "bb_upper": 2079.18, "bb_mid": 2060.5, "bb_lower": 2041.82}, {"date": "2026-02-03", "open": 2055.0, "high": 2060.0, "low": 2055.0, "close": 2060.0, "volume": 251, "ma5": 2062.0, "ma20": 2061.25, "ma60": 2050.95, "ma120": 2041.99, "rsi": 50.74, "macd": 3.03, "macd_signal": 4.34, "macd_hist": -1.3, "bb_upper": 2078.53, "bb_mid": 2061.25, "bb_lower": 2043.97}, {"date": "2026-02-04", "open": 2060.0, "high": 2075.0, "low": 2055.0, "close": 2075.0, "volume": 3571, "ma5": 2062.0, "ma20": 2062.75, "ma60": 2051.37, "ma120": 2042.45, "rsi": 58.52, "macd": 3.84, "macd_signal": 4.24, "macd_hist": -0.4, "bb_upper": 2079.33, "bb_mid": 2062.75, "bb_lower": 2046.17}, {"date": "2026-02-05", "open": 2060.0, "high": 2070.0, "low": 2055.0, "close": 2070.0, "volume": 10745, "ma5": 2062.0, "ma20": 2063.75, "ma60": 2051.87, "ma120": 2042.95, "rsi": 55.38, "macd": 4.03, "macd_signal": 4.2, "macd_hist": -0.17, "bb_upper": 2079.52, "bb_mid": 2063.75, "bb_lower": 2047.98}, {"date": "2026-02-06", "open": 2060.0, "high": 2065.0, "low": 2060.0, "close": 2065.0, "volume": 4336, "ma5": 2065.0, "ma20": 2064.25, "ma60": 2052.28, "ma120": 2043.32, "rsi": 52.35, "macd": 3.73, "macd_signal": 4.1, "macd_hist": -0.37, "bb_upper": 2079.51, "bb_mid": 2064.25, "bb_lower": 2048.99}, {"date": "2026-02-09", "open": 2065.0, "high": 2125.0, "low": 2060.0, "close": 2105.0, "volume": 30357, "ma5": 2075.0, "ma20": 2066.5, "ma60": 2053.53, "ma120": 2044.03, "rsi": 67.6, "macd": 6.65, "macd_signal": 4.61, "macd_hist": 2.04, "bb_upper": 2089.76, "bb_mid": 2066.5, "bb_lower": 2043.24}, {"date": "2026-02-10", "open": 2100.0, "high": 2105.0, "low": 2080.0, "close": 2095.0, "volume": 5560, "ma5": 2082.0, "ma20": 2068.5, "ma60": 2054.62, "ma120": 2044.66, "rsi": 62.24, "macd": 8.06, "macd_signal": 5.3, "macd_hist": 2.76, "bb_upper": 2094.21, "bb_mid": 2068.5, "bb_lower": 2042.79}, {"date": "2026-02-11", "open": 2080.0, "high": 2090.0, "low": 2070.0, "close": 2070.0, "volume": 5061, "ma5": 2081.0, "ma20": 2069.25, "ma60": 2055.28, "ma120": 2045.03, "rsi": 51.29, "macd": 7.08, "macd_signal": 5.66, "macd_hist": 1.42, "bb_upper": 2094.2, "bb_mid": 2069.25, "bb_lower": 2044.3}, {"date": "2026-02-12", "open": 2070.0, "high": 2075.0, "low": 2070.0, "close": 2070.0, "volume": 2276, "ma5": 2081.0, "ma20": 2069.75, "ma60": 2055.87, "ma120": 2045.41, "rsi": 51.29, "macd": 6.23, "macd_signal": 5.77, "macd_hist": 0.46, "bb_upper": 2094.34, "bb_mid": 2069.75, "bb_lower": 2045.16}, {"date": "2026-02-13", "open": 2070.0, "high": 2075.0, "low": 2070.0, "close": 2070.0, "volume": 2111, "ma5": 2082.0, "ma20": 2070.25, "ma60": 2056.45, "ma120": 2045.82, "rsi": 51.29, "macd": 5.49, "macd_signal": 5.72, "macd_hist": -0.22, "bb_upper": 2094.43, "bb_mid": 2070.25, "bb_lower": 2046.07}, {"date": "2026-02-19", "open": 2080.0, "high": 2080.0, "low": 2070.0, "close": 2070.0, "volume": 2504, "ma5": 2075.0, "ma20": 2070.75, "ma60": 2057.03, "ma120": 2046.24, "rsi": 51.29, "macd": 4.85, "macd_signal": 5.54, "macd_hist": -0.69, "bb_upper": 2094.47, "bb_mid": 2070.75, "bb_lower": 2047.03}, {"date": "2026-02-20", "open": 2070.0, "high": 2135.0, "low": 2070.0, "close": 2115.0, "volume": 22206, "ma5": 2079.0, "ma20": 2072.75, "ma60": 2058.45, "ma120": 2046.99, "rsi": 65.84, "macd": 7.89, "macd_signal": 6.01, "macd_hist": 1.88, "bb_upper": 2103.32, "bb_mid": 2072.75, "bb_lower": 2042.18}, {"date": "2026-02-23", "open": 2085.0, "high": 2120.0, "low": 2085.0, "close": 2115.0, "volume": 5285, "ma5": 2088.0, "ma20": 2075.25, "ma60": 2059.78, "ma120": 2047.78, "rsi": 65.84, "macd": 10.17, "macd_signal": 6.84, "macd_hist": 3.33, "bb_upper": 2110.67, "bb_mid": 2075.25, "bb_lower": 2039.83}, {"date": "2026-02-24", "open": 2110.0, "high": 2115.0, "low": 2100.0, "close": 2110.0, "volume": 1593, "ma5": 2096.0, "ma20": 2077.75, "ma60": 2061.12, "ma120": 2048.53, "rsi": 63.4, "macd": 11.45, "macd_signal": 7.77, "macd_hist": 3.69, "bb_upper": 2115.5, "bb_mid": 2077.75, "bb_lower": 2040.0}, {"date": "2026-02-25", "open": 2090.0, "high": 2100.0, "low": 2085.0, "close": 2100.0, "volume": 545, "ma5": 2102.0, "ma20": 2079.25, "ma60": 2062.28, "ma120": 2049.24, "rsi": 58.71, "macd": 11.52, "macd_signal": 8.52, "macd_hist": 3.01, "bb_upper": 2118.02, "bb_mid": 2079.25, "bb_lower": 2040.48}, {"date": "2026-02-26", "open": 2085.0, "high": 2095.0, "low": 2080.0, "close": 2090.0, "volume": 2729, "ma5": 2106.0, "ma20": 2080.0, "ma60": 2063.12, "ma120": 2049.89, "rsi": 54.38, "macd": 10.65, "macd_signal": 8.94, "macd_hist": 1.71, "bb_upper": 2118.99, "bb_mid": 2080.0, "bb_lower": 2041.01}, {"date": "2026-02-27", "open": 2090.0, "high": 2105.0, "low": 2090.0, "close": 2090.0, "volume": 5003, "ma5": 2101.0, "ma20": 2081.0, "ma60": 2063.78, "ma120": 2050.56, "rsi": 54.38, "macd": 9.85, "macd_signal": 9.12, "macd_hist": 0.72, "bb_upper": 2119.94, "bb_mid": 2081.0, "bb_lower": 2042.06}, {"date": "2026-03-03", "open": 2085.0, "high": 2100.0, "low": 2085.0, "close": 2100.0, "volume": 3893, "ma5": 2098.0, "ma20": 2082.25, "ma60": 2064.62, "ma120": 2051.27, "rsi": 57.98, "macd": 9.9, "macd_signal": 9.28, "macd_hist": 0.62, "bb_upper": 2121.93, "bb_mid": 2082.25, "bb_lower": 2042.57}, {"date": "2026-03-04", "open": 2090.0, "high": 2090.0, "low": 2070.0, "close": 2085.0, "volume": 6038, "ma5": 2093.0, "ma20": 2083.0, "ma60": 2065.2, "ma120": 2051.85, "rsi": 51.43, "macd": 8.63, "macd_signal": 9.15, "macd_hist": -0.52, "bb_upper": 2122.29, "bb_mid": 2083.0, "bb_lower": 2043.71}, {"date": "2026-03-05", "open": 2095.0, "high": 2095.0, "low": 2080.0, "close": 2085.0, "volume": 693, "ma5": 2090.0, "ma20": 2084.75, "ma60": 2065.78, "ma120": 2052.43, "rsi": 51.43, "macd": 7.54, "macd_signal": 8.83, "macd_hist": -1.29, "bb_upper": 2121.01, "bb_mid": 2084.75, "bb_lower": 2048.49}, {"date": "2026-03-06", "open": 2095.0, "high": 2100.0, "low": 2080.0, "close": 2100.0, "volume": 698, "ma5": 2092.0, "ma20": 2087.0, "ma60": 2066.28, "ma120": 2053.14, "rsi": 57.05, "macd": 7.8, "macd_signal": 8.62, "macd_hist": -0.82, "bb_upper": 2121.12, "bb_mid": 2087.0, "bb_lower": 2052.88}, {"date": "2026-03-09", "open": 2060.0, "high": 2115.0, "low": 2050.0, "close": 2085.0, "volume": 13158, "ma5": 2091.0, "ma20": 2088.25, "ma60": 2066.45, "ma120": 2053.56, "rsi": 50.73, "macd": 6.71, "macd_signal": 8.24, "macd_hist": -1.53, "bb_upper": 2120.07, "bb_mid": 2088.25, "bb_lower": 2056.43}, {"date": "2026-03-10", "open": 2085.0, "high": 2105.0, "low": 2085.0, "close": 2090.0, "volume": 25976, "ma5": 2089.0, "ma20": 2089.0, "ma60": 2066.7, "ma120": 2054.06, "rsi": 52.61, "macd": 6.19, "macd_signal": 7.83, "macd_hist": -1.64, "bb_upper": 2120.24, "bb_mid": 2089.0, "bb_lower": 2057.76}, {"date": "2026-03-11", "open": 2090.0, "high": 2100.0, "low": 2080.0, "close": 2080.0, "volume": 279, "ma5": 2088.0, "ma20": 2089.5, "ma60": 2066.62, "ma120": 2054.52, "rsi": 48.61, "macd": 4.91, "macd_signal": 7.25, "macd_hist": -2.34, "bb_upper": 2119.82, "bb_mid": 2089.5, "bb_lower": 2059.18}, {"date": "2026-03-12", "open": 2100.0, "high": 2100.0, "low": 2085.0, "close": 2085.0, "volume": 17478, "ma5": 2088.0, "ma20": 2090.5, "ma60": 2066.78, "ma120": 2054.98, "rsi": 50.63, "macd": 4.24, "macd_signal": 6.65, "macd_hist": -2.4, "bb_upper": 2118.77, "bb_mid": 2090.5, "bb_lower": 2062.23}, {"date": "2026-03-13", "open": 2085.0, "high": 2105.0, "low": 2080.0, "close": 2090.0, "volume": 25730, "ma5": 2086.0, "ma20": 2089.75, "ma60": 2067.12, "ma120": 2055.52, "rsi": 52.64, "macd": 4.08, "macd_signal": 6.13, "macd_hist": -2.05, "bb_upper": 2117.22, "bb_mid": 2089.75, "bb_lower": 2062.28}, {"date": "2026-03-16", "open": 2085.0, "high": 2085.0, "low": 2065.0, "close": 2075.0, "volume": 5212, "ma5": 2084.0, "ma20": 2088.75, "ma60": 2067.28, "ma120": 2055.93, "rsi": 46.52, "macd": 2.7, "macd_signal": 5.45, "macd_hist": -2.74, "bb_upper": 2116.83, "bb_mid": 2088.75, "bb_lower": 2060.67}, {"date": "2026-03-17", "open": 2075.0, "high": 2085.0, "low": 2075.0, "close": 2075.0, "volume": 3150, "ma5": 2081.0, "ma20": 2089.0, "ma60": 2067.62, "ma120": 2056.39, "rsi": 46.52, "macd": 1.6, "macd_signal": 4.68, "macd_hist": -3.08, "bb_upper": 2116.5, "bb_mid": 2089.0, "bb_lower": 2061.5}, {"date": "2026-03-18", "open": 2075.0, "high": 2095.0, "low": 2060.0, "close": 2095.0, "volume": 20122, "ma5": 2084.0, "ma20": 2090.25, "ma60": 2068.7, "ma120": 2056.93, "rsi": 54.67, "macd": 2.3, "macd_signal": 4.2, "macd_hist": -1.9, "bb_upper": 2116.42, "bb_mid": 2090.25, "bb_lower": 2064.08}, {"date": "2026-03-19", "open": 2080.0, "high": 2080.0, "low": 2080.0, "close": 2080.0, "volume": 1, "ma5": 2083.0, "ma20": 2090.75, "ma60": 2069.53, "ma120": 2057.35, "rsi": 48.68, "macd": 1.64, "macd_signal": 3.69, "macd_hist": -2.05, "bb_upper": 2115.7, "bb_mid": 2090.75, "bb_lower": 2065.8}, {"date": "2026-03-20", "open": 2070.0, "high": 2100.0, "low": 2070.0, "close": 2085.0, "volume": 9141, "ma5": 2082.0, "ma20": 2091.5, "ma60": 2070.28, "ma120": 2057.81, "rsi": 50.62, "macd": 1.5, "macd_signal": 3.25, "macd_hist": -1.75, "bb_upper": 2114.76, "bb_mid": 2091.5, "bb_lower": 2068.24}, {"date": "2026-03-23", "open": 2070.0, "high": 2095.0, "low": 2070.0, "close": 2090.0, "volume": 10732, "ma5": 2085.0, "ma20": 2090.25, "ma60": 2071.12, "ma120": 2058.31, "rsi": 52.55, "macd": 1.77, "macd_signal": 2.95, "macd_hist": -1.19, "bb_upper": 2110.86, "bb_mid": 2090.25, "bb_lower": 2069.64}, {"date": "2026-03-24", "open": 2095.0, "high": 2100.0, "low": 2090.0, "close": 2090.0, "volume": 6676, "ma5": 2088.0, "ma20": 2089.0, "ma60": 2072.03, "ma120": 2058.81, "rsi": 52.55, "macd": 1.96, "macd_signal": 2.75, "macd_hist": -0.8, "bb_upper": 2106.2, "bb_mid": 2089.0, "bb_lower": 2071.8}, {"date": "2026-03-25", "open": 2080.0, "high": 2090.0, "low": 2070.0, "close": 2070.0, "volume": 5057, "ma5": 2083.0, "ma20": 2087.0, "ma60": 2072.53, "ma120": 2059.14, "rsi": 44.48, "macd": 0.49, "macd_signal": 2.3, "macd_hist": -1.81, "bb_upper": 2103.25, "bb_mid": 2087.0, "bb_lower": 2070.75}, {"date": "2026-03-26", "open": 2065.0, "high": 2090.0, "low": 2065.0, "close": 2075.0, "volume": 16390, "ma5": 2082.0, "ma20": 2085.75, "ma60": 2073.03, "ma120": 2059.48, "rsi": 46.68, "macd": -0.27, "macd_signal": 1.79, "macd_hist": -2.05, "bb_upper": 2101.65, "bb_mid": 2085.75, "bb_lower": 2069.85}, {"date": "2026-03-27", "open": 2075.0, "high": 2075.0, "low": 2070.0, "close": 2070.0, "volume": 1719, "ma5": 2079.0, "ma20": 2084.75, "ma60": 2073.53, "ma120": 2059.77, "rsi": 44.77, "macd": -1.26, "macd_signal": 1.18, "macd_hist": -2.43, "bb_upper": 2101.92, "bb_mid": 2084.75, "bb_lower": 2067.58}, {"date": "2026-03-30", "open": 2065.0, "high": 2070.0, "low": 2065.0, "close": 2070.0, "volume": 1109, "ma5": 2075.0, "ma20": 2083.75, "ma60": 2073.95, "ma120": 2060.06, "rsi": 44.77, "macd": -2.02, "macd_signal": 0.54, "macd_hist": -2.56, "bb_upper": 2101.88, "bb_mid": 2083.75, "bb_lower": 2065.62}, {"date": "2026-03-31", "open": 2065.0, "high": 2080.0, "low": 2060.0, "close": 2070.0, "volume": 7201, "ma5": 2071.0, "ma20": 2082.25, "ma60": 2074.37, "ma120": 2060.31, "rsi": 44.77, "macd": -2.59, "macd_signal": -0.09, "macd_hist": -2.5, "bb_upper": 2099.71, "bb_mid": 2082.25, "bb_lower": 2064.79}, {"date": "2026-04-01", "open": 2065.0, "high": 2065.0, "low": 2060.0, "close": 2060.0, "volume": 3618, "ma5": 2069.0, "ma20": 2081.0, "ma60": 2074.53, "ma120": 2060.43, "rsi": 40.6, "macd": -3.8, "macd_signal": -0.83, "macd_hist": -2.98, "bb_upper": 2100.9, "bb_mid": 2081.0, "bb_lower": 2061.1}, {"date": "2026-04-02", "open": 2055.0, "high": 2055.0, "low": 2040.0, "close": 2055.0, "volume": 25226, "ma5": 2065.0, "ma20": 2079.5, "ma60": 2074.7, "ma120": 2060.56, "rsi": 38.67, "macd": -5.11, "macd_signal": -1.69, "macd_hist": -3.43, "bb_upper": 2102.28, "bb_mid": 2079.5, "bb_lower": 2056.72}, {"date": "2026-04-03", "open": 2050.0, "high": 2055.0, "low": 2040.0, "close": 2055.0, "volume": 13618, "ma5": 2062.0, "ma20": 2077.25, "ma60": 2074.92, "ma120": 2060.6, "rsi": 38.67, "macd": -6.08, "macd_signal": -2.57, "macd_hist": -3.52, "bb_upper": 2100.37, "bb_mid": 2077.25, "bb_lower": 2054.13}, {"date": "2026-04-06", "open": 2050.0, "high": 2055.0, "low": 2045.0, "close": 2055.0, "volume": 10032, "ma5": 2059.0, "ma20": 2075.75, "ma60": 2075.08, "ma120": 2060.68, "rsi": 38.67, "macd": -6.77, "macd_signal": -3.41, "macd_hist": -3.36, "bb_upper": 2100.5, "bb_mid": 2075.75, "bb_lower": 2051.0}, {"date": "2026-04-07", "open": 2050.0, "high": 2055.0, "low": 2040.0, "close": 2050.0, "volume": 7012, "ma5": 2055.0, "ma20": 2073.75, "ma60": 2075.17, "ma120": 2060.72, "rsi": 36.49, "macd": -7.63, "macd_signal": -4.25, "macd_hist": -3.38, "bb_upper": 2099.99, "bb_mid": 2073.75, "bb_lower": 2047.51}, {"date": "2026-04-08", "open": 2045.0, "high": 2050.0, "low": 2040.0, "close": 2050.0, "volume": 53621, "ma5": 2053.0, "ma20": 2072.25, "ma60": 2075.17, "ma120": 2060.77, "rsi": 36.49, "macd": -8.22, "macd_signal": -5.04, "macd_hist": -3.17, "bb_upper": 2100.26, "bb_mid": 2072.25, "bb_lower": 2044.24}, {"date": "2026-04-09", "open": 2045.0, "high": 2050.0, "low": 2040.0, "close": 2045.0, "volume": 16287, "ma5": 2051.0, "ma20": 2070.25, "ma60": 2075.0, "ma120": 2060.81, "rsi": 34.26, "macd": -8.98, "macd_signal": -5.83, "macd_hist": -3.15, "bb_upper": 2099.99, "bb_mid": 2070.25, "bb_lower": 2040.51}, {"date": "2026-04-10", "open": 2045.0, "high": 2050.0, "low": 2040.0, "close": 2045.0, "volume": 23352, "ma5": 2049.0, "ma20": 2068.0, "ma60": 2074.75, "ma120": 2060.77, "rsi": 34.26, "macd": -9.48, "macd_signal": -6.56, "macd_hist": -2.92, "bb_upper": 2098.23, "bb_mid": 2068.0, "bb_lower": 2037.77}, {"date": "2026-04-13", "open": 2045.0, "high": 2050.0, "low": 2040.0, "close": 2040.0, "volume": 24113, "ma5": 2046.0, "ma20": 2066.25, "ma60": 2074.5, "ma120": 2060.68, "rsi": 31.99, "macd": -10.16, "macd_signal": -7.28, "macd_hist": -2.88, "bb_upper": 2098.63, "bb_mid": 2066.25, "bb_lower": 2033.87}, {"date": "2026-04-14", "open": 2040.0, "high": 2050.0, "low": 2040.0, "close": 2050.0, "volume": 26954, "ma5": 2046.0, "ma20": 2065.0, "ma60": 2074.42, "ma120": 2060.68, "rsi": 40.49, "macd": -9.78, "macd_signal": -7.78, "macd_hist": -2.0, "bb_upper": 2097.86, "bb_mid": 2065.0, "bb_lower": 2032.14}, {"date": "2026-04-15", "open": 2050.0, "high": 2075.0, "low": 2040.0, "close": 2055.0, "volume": 30380, "ma5": 2047.0, "ma20": 2063.0, "ma60": 2074.33, "ma120": 2060.72, "rsi": 44.24, "macd": -8.97, "macd_signal": -8.02, "macd_hist": -0.95, "bb_upper": 2093.07, "bb_mid": 2063.0, "bb_lower": 2032.93}, {"date": "2026-04-16", "open": 2050.0, "high": 2050.0, "low": 2045.0, "close": 2045.0, "volume": 1573, "ma5": 2047.0, "ma20": 2061.25, "ma60": 2074.08, "ma120": 2060.64, "rsi": 38.95, "macd": -9.04, "macd_signal": -8.22, "macd_hist": -0.81, "bb_upper": 2091.23, "bb_mid": 2061.25, "bb_lower": 2031.27}, {"date": "2026-04-17", "open": 2045.0, "high": 2045.0, "low": 2040.0, "close": 2045.0, "volume": 26805, "ma5": 2047.0, "ma20": 2059.25, "ma60": 2073.83, "ma120": 2060.64, "rsi": 38.95, "macd": -8.98, "macd_signal": -8.37, "macd_hist": -0.61, "bb_upper": 2087.93, "bb_mid": 2059.25, "bb_lower": 2030.57}, {"date": "2026-04-20", "open": 2045.0, "high": 2045.0, "low": 2040.0, "close": 2040.0, "volume": 11275, "ma5": 2047.0, "ma20": 2056.75, "ma60": 2073.25, "ma120": 2060.56, "rsi": 36.43, "macd": -9.24, "macd_signal": -8.55, "macd_hist": -0.69, "bb_upper": 2082.88, "bb_mid": 2056.75, "bb_lower": 2030.62}, {"date": "2026-04-21", "open": 2045.0, "high": 2045.0, "low": 2030.0, "close": 2040.0, "volume": 38265, "ma5": 2045.0, "ma20": 2054.25, "ma60": 2072.83, "ma120": 2060.56, "rsi": 36.43, "macd": -9.33, "macd_signal": -8.7, "macd_hist": -0.63, "bb_upper": 2076.45, "bb_mid": 2054.25, "bb_lower": 2032.05}, {"date": "2026-04-22", "open": 2040.0, "high": 2040.0, "low": 2035.0, "close": 2040.0, "volume": 682, "ma5": 2042.0, "ma20": 2052.75, "ma60": 2072.5, "ma120": 2060.52, "rsi": 36.43, "macd": -9.3, "macd_signal": -8.82, "macd_hist": -0.47, "bb_upper": 2074.54, "bb_mid": 2052.75, "bb_lower": 2030.96}, {"date": "2026-04-23", "open": 2040.0, "high": 2045.0, "low": 2035.0, "close": 2040.0, "volume": 15741, "ma5": 2041.0, "ma20": 2051.0, "ma60": 2072.0, "ma120": 2060.43, "rsi": 36.43, "macd": -9.16, "macd_signal": -8.89, "macd_hist": -0.27, "bb_upper": 2070.9, "bb_mid": 2051.0, "bb_lower": 2031.1}, {"date": "2026-04-24", "open": 2035.0, "high": 2040.0, "low": 2035.0, "close": 2040.0, "volume": 12584, "ma5": 2040.0, "ma20": 2049.5, "ma60": 2071.42, "ma120": 2060.35, "rsi": 36.43, "macd": -8.96, "macd_signal": -8.9, "macd_hist": -0.05, "bb_upper": 2067.91, "bb_mid": 2049.5, "bb_lower": 2031.09}, {"date": "2026-04-27", "open": 2030.0, "high": 2040.0, "low": 2027.0, "close": 2040.0, "volume": 2044, "ma5": 2040.0, "ma20": 2048.0, "ma60": 2070.92, "ma120": 2060.31, "rsi": 36.43, "macd": -8.69, "macd_signal": -8.86, "macd_hist": 0.17, "bb_upper": 2064.25, "bb_mid": 2048.0, "bb_lower": 2031.75}, {"date": "2026-04-28", "open": 2035.0, "high": 2035.0, "low": 2025.0, "close": 2030.0, "volume": 16108, "ma5": 2038.0, "ma20": 2046.0, "ma60": 2070.17, "ma120": 2060.14, "rsi": 30.3, "macd": -9.18, "macd_signal": -8.93, "macd_hist": -0.26, "bb_upper": 2060.7, "bb_mid": 2046.0, "bb_lower": 2031.3}, {"date": "2026-04-29", "open": 2030.0, "high": 2030.0, "low": 2020.0, "close": 2025.0, "volume": 6476, "ma5": 2035.0, "ma20": 2044.25, "ma60": 2069.42, "ma120": 2060.02, "rsi": 27.78, "macd": -9.86, "macd_signal": -9.11, "macd_hist": -0.75, "bb_upper": 2060.15, "bb_mid": 2044.25, "bb_lower": 2028.35}, {"date": "2026-04-30", "open": 2030.0, "high": 2030.0, "low": 2020.0, "close": 2020.0, "volume": 19098, "ma5": 2031.0, "ma20": 2042.5, "ma60": 2068.92, "ma120": 2059.77, "rsi": 25.5, "macd": -10.68, "macd_signal": -9.43, "macd_hist": -1.25, "bb_upper": 2060.8, "bb_mid": 2042.5, "bb_lower": 2024.2}]